<?xml version = '1.0' encoding = 'UTF-8'?>
<FKIndexAssociation class="oracle.dbtools.crest.model.design.relational.FKIndexAssociation" directorySegmentName="seg_0" id="D3D8B39C-0499-4A3D-8BE3-82AA1D5EB9CC" containerWithKeyObject="5CB7B07A-47FD-77B3-73DF-3C9CE741167C" localFKIndex="729809B5-5ED8-3934-DD1A-BA9A88705B97" name="CLLTRL_RL_CLLTRL_FK">
<createdBy>nuvolia</createdBy>
<createdTime>2026-02-06 11:04:36 UTC</createdTime>
<generatorID>6045DE7C-B438-877A-8EBF-E49F3DEAFC5C</generatorID>
<ownerDesignName>BIRD data models</ownerDesignName>
<referredTableLongName>CLLTRL</referredTableLongName>
<deleteRule>NO ACTION</deleteRule>
<referredTableID>564BCD37-65A0-BB18-6D8B-9A81B0870863</referredTableID>
<keyObject>380B8B11-4EF8-7370-6FC2-DF98850D011C</keyObject>
<referredKeyID>380B8B11-4EF8-7370-6FC2-DF98850D011C</referredKeyID>
<mandatory>true</mandatory>
<refColNames>CLLTRL_RFRNC_DT,CLLTRL_RPRTNG_AGNT_ID,CLLTRL_ACCNTNG_CNSLDTN_LVL,CLLTRL_ACCNTNG_STNDRD,CLLTRL_ID</refColNames>
<transferable>true</transferable>
<rely>false</rely>
<columnDependencyConstraintGenerateInDDL>true</columnDependencyConstraintGenerateInDDL>
</FKIndexAssociation>
