<?xml version = '1.0' encoding = 'UTF-8'?>
<Diagram class="oracle.dbtools.crest.swingui.logical.DPVLogicalSubView" name="Introduction to the LDM - Enterprise size information" id="8629E382-5D62-F508-C55F-8C41EB12556D">
<createdBy>BIRD Work Stream on Data Modelling</createdBy>
<modifiedBy>nuvolia</modifiedBy>
<createdTime>2025-01-22 08:09:34 UTC</createdTime>
<autoRoute>false</autoRoute>
<boxInbox>false</boxInbox>
<showLegend>false</showLegend>
<showLabels>false</showLabels>
<showRelAttributes>false</showRelAttributes>
<gridEnabled>false</gridEnabled>
<showGrid>false</showGrid>
<diagramColor>-1</diagramColor>
<legendAttributes>98</legendAttributes>
<display>false</display>
<notation>2</notation>
<showAllDetails>false</showAllDetails>
<showComments>true</showComments>
<showElements>true</showElements>
<propertyMap>
<property name="Disclaimer" value="Although great care has been put into creating this logical data model and supporting documents, no guarantee can be given with regards to the technical correctness of the content"/>
<property name="Version" value="6.5.0"/>
</propertyMap>
<objectViews>
<OView class="oracle.dbtools.crest.swingui.logical.TVEntity" oid="36F4F142-0055-6B37-EB1E-64DFB173402F" otype="Entity" vid="55F2E470-4E28-2E95-2B5F-8F543DF21816">
<hideElementsInCurrentOnly>false</hideElementsInCurrentOnly>
<bounds x="19" y="368" width="414" height="300"/>
</OView>
<OView class="oracle.dbtools.crest.swingui.logical.TVEntity" oid="5D7D7500-0027-058E-2A37-50FD8F024CED" otype="Entity" vid="B456EBCD-3684-B87F-E8B0-0F08B7CA3557">
<hideElementsInCurrentOnly>false</hideElementsInCurrentOnly>
<bounds x="424" y="758" width="251" height="112"/>
</OView>
<OView class="oracle.dbtools.crest.swingui.logical.TVEntity" oid="640F6922-F9EE-51D8-1152-A6AE271F0417" otype="Entity" vid="703CF72F-54C9-D34B-B977-EB8F36F403C2">
<hideElementsInCurrentOnly>false</hideElementsInCurrentOnly>
<bounds x="12" y="690" width="164" height="41"/>
</OView>
<OView class="oracle.dbtools.crest.swingui.logical.TVEntity" oid="68582837-AD3C-8E9C-DB5E-68322CD1DE08" otype="Entity" vid="A29DD5AB-0C62-DB1D-2171-2924465CE85A">
<hideElementsInCurrentOnly>false</hideElementsInCurrentOnly>
<bounds x="220" y="0" width="468" height="170"/>
</OView>
<OView class="oracle.dbtools.crest.swingui.logical.TVEntity" oid="6B124BC2-A918-3C18-5BC9-C01912E19508" otype="Entity" vid="7297B848-F860-FD3D-6813-A427831955BB">
<hideElementsInCurrentOnly>false</hideElementsInCurrentOnly>
<bounds x="1001" y="273" width="140" height="40"/>
</OView>
<OView class="oracle.dbtools.crest.swingui.logical.TVEntity" oid="85956057-D0C7-8869-F90B-A6A301A3A30F" otype="Entity" vid="CF40381D-FFA0-3FDD-9BE7-A3966123DB15">
<hideElementsInCurrentOnly>false</hideElementsInCurrentOnly>
<bounds x="58" y="758" width="348" height="134"/>
</OView>
<OView class="oracle.dbtools.crest.swingui.logical.TVEntity" oid="9BC3536B-8321-4DC1-DBFD-E8B4652D40E2" otype="Entity" vid="49BE351B-E481-BE6F-FA6B-559C50285089">
<hideElementsInCurrentOnly>false</hideElementsInCurrentOnly>
<bounds x="658" y="368" width="246" height="184"/>
</OView>
<OView class="oracle.dbtools.crest.swingui.logical.TVEntity" oid="B1F895CA-E612-3482-70D5-3578E2C60A8B" otype="Entity" vid="7EF6BFCA-34C9-475B-CFFA-4F213B6FB856">
<hideElementsInCurrentOnly>false</hideElementsInCurrentOnly>
<bounds x="164" y="208" width="292" height="112"/>
</OView>
<OView class="oracle.dbtools.crest.swingui.logical.TVEntity" oid="D457AA83-122D-7CA4-C95B-BF2AA279A7F7" otype="Entity" vid="572BC216-410A-29F0-8F07-1844069EDFBC">
<hideElementsInCurrentOnly>false</hideElementsInCurrentOnly>
<bounds x="449" y="368" width="191" height="115"/>
</OView>
<OView class="oracle.dbtools.crest.swingui.logical.TVEntity" oid="DD58D100-8E07-C96E-9247-8C2B3E9E64FE" otype="Entity" vid="FE878B05-A22B-0F3A-10E9-D47ECFE9AA63">
<hideElementsInCurrentOnly>false</hideElementsInCurrentOnly>
<bounds x="479" y="273" width="200" height="40"/>
</OView>
</objectViews>
<connectors>
<Connector class="oracle.dbtools.crest.swingui.logical.TVInheritanceRelation" oid="30BA04D7-FD69-55EB-32BE-4D9FBA07E3E9" otype="Hierarchy relation" vid_source="55F2E470-4E28-2E95-2B5F-8F543DF21816" vid_target="CF40381D-FFA0-3FDD-9BE7-A3966123DB15">
<hideElementsInCurrentOnly>false</hideElementsInCurrentOnly>
<backgroundColor>-65536</backgroundColor>
<lineWidth>1</lineWidth>
<points>
<point x="232" y="668"/>
<point x="232" y="758"/>
</points>
</Connector>
<Connector class="oracle.dbtools.crest.swingui.logical.TVRelation" oid="31D60F69-937A-BC75-BFAE-5C2B40AB06FA" otype="Relation" vid_source="7297B848-F860-FD3D-6813-A427831955BB" vid_target="A29DD5AB-0C62-DB1D-2171-2924465CE85A">
<hideElementsInCurrentOnly>false</hideElementsInCurrentOnly>
<backgroundColor>-16777216</backgroundColor>
<lineWidth>1</lineWidth>
<points>
<point x="1071" y="313"/>
<point x="1071" y="368"/>
</points>
</Connector>
<Connector class="oracle.dbtools.crest.swingui.logical.TVRelation" oid="878F27C3-1FF6-0F79-A43D-04046BEC14B6" otype="Relation" vid_source="A29DD5AB-0C62-DB1D-2171-2924465CE85A" vid_target="49BE351B-E481-BE6F-FA6B-559C50285089">
<hideElementsInCurrentOnly>false</hideElementsInCurrentOnly>
<backgroundColor>-16777216</backgroundColor>
<lineWidth>1</lineWidth>
<points>
<point x="616" y="170"/>
<point x="772" y="368"/>
</points>
</Connector>
<Connector class="oracle.dbtools.crest.swingui.logical.TVRelation" oid="8CEC72B1-CE3F-BDE1-0210-0452A878CD15" otype="Relation" vid_source="703CF72F-54C9-D34B-B977-EB8F36F403C2" vid_target="CF40381D-FFA0-3FDD-9BE7-A3966123DB15">
<hideElementsInCurrentOnly>false</hideElementsInCurrentOnly>
<backgroundColor>-16777216</backgroundColor>
<lineWidth>1</lineWidth>
<points>
<point x="117" y="731"/>
<point x="117" y="758"/>
</points>
</Connector>
<Connector class="oracle.dbtools.crest.swingui.logical.TVInheritanceRelation" oid="9F9D1B12-E6F7-374E-4B59-54BC7B944AEE" otype="Hierarchy relation" vid_source="7EF6BFCA-34C9-475B-CFFA-4F213B6FB856" vid_target="572BC216-410A-29F0-8F07-1844069EDFBC">
<hideElementsInCurrentOnly>false</hideElementsInCurrentOnly>
<backgroundColor>-65536</backgroundColor>
<lineWidth>1</lineWidth>
<points>
<point x="452" y="320"/>
<point x="452" y="368"/>
</points>
</Connector>
<Connector class="oracle.dbtools.crest.swingui.logical.TVInheritanceRelation" oid="AC2B9816-FC96-3AC1-BA13-FF076F39E0AE" otype="Hierarchy relation" vid_source="572BC216-410A-29F0-8F07-1844069EDFBC" vid_target="B456EBCD-3684-B87F-E8B0-0F08B7CA3557">
<hideElementsInCurrentOnly>false</hideElementsInCurrentOnly>
<backgroundColor>-65536</backgroundColor>
<lineWidth>1</lineWidth>
<points>
<point x="544" y="483"/>
<point x="544" y="758"/>
</points>
</Connector>
<Connector class="oracle.dbtools.crest.swingui.logical.TVInheritanceRelation" oid="B06276DA-24C3-040A-D1DF-AC827FCDA934" otype="Hierarchy relation" vid_source="7EF6BFCA-34C9-475B-CFFA-4F213B6FB856" vid_target="55F2E470-4E28-2E95-2B5F-8F543DF21816">
<hideElementsInCurrentOnly>false</hideElementsInCurrentOnly>
<backgroundColor>-65536</backgroundColor>
<lineWidth>1</lineWidth>
<points>
<point x="298" y="320"/>
<point x="298" y="368"/>
</points>
</Connector>
<Connector class="oracle.dbtools.crest.swingui.logical.TVRelation" oid="B0EB9733-6B90-BA77-390B-1EC67ADE9E76" otype="Relation" vid_source="55F2E470-4E28-2E95-2B5F-8F543DF21816" vid_target="55F2E470-4E28-2E95-2B5F-8F543DF21816">
<hideElementsInCurrentOnly>false</hideElementsInCurrentOnly>
<backgroundColor>-16777216</backgroundColor>
<lineWidth>1</lineWidth>
<points>
<point x="433" y="544"/>
<point x="458" y="544"/>
<point x="458" y="691"/>
<point x="262" y="691"/>
<point x="262" y="668"/>
</points>
</Connector>
<Connector class="oracle.dbtools.crest.swingui.logical.TVInheritanceRelation" oid="BB577665-AFBE-D1B7-D966-D06F98F957B5" otype="Hierarchy relation" vid_source="A29DD5AB-0C62-DB1D-2171-2924465CE85A" vid_target="7EF6BFCA-34C9-475B-CFFA-4F213B6FB856">
<hideElementsInCurrentOnly>false</hideElementsInCurrentOnly>
<backgroundColor>-65536</backgroundColor>
<lineWidth>1</lineWidth>
<points>
<point x="338" y="170"/>
<point x="338" y="208"/>
</points>
</Connector>
<Connector class="oracle.dbtools.crest.swingui.logical.TVRelation" oid="FA930BF5-26EC-3CEF-2467-56A9D5EB7FBD" otype="Relation" vid_source="FE878B05-A22B-0F3A-10E9-D47ECFE9AA63" vid_target="49BE351B-E481-BE6F-FA6B-559C50285089">
<hideElementsInCurrentOnly>false</hideElementsInCurrentOnly>
<backgroundColor>-16777216</backgroundColor>
<lineWidth>1</lineWidth>
<points>
<point x="668" y="313"/>
<point x="668" y="368"/>
</points>
</Connector>
</connectors>
<arcs>
<Arc class="oracle.dbtools.crest.swingui.logical.TVArc" oid="E552193B-BDBD-9A42-B55A-9463549391F1" otype="Arc" vid="6F647826-0F82-E3ED-A1EF-37F52E587137">
<hideElementsInCurrentOnly>false</hideElementsInCurrentOnly>
<bounds x="144" y="188" width="332" height="152"/>
</Arc>
</arcs>
</Diagram>
