<?xml version = '1.0' encoding = 'UTF-8'?>
<Diagram class="oracle.dbtools.crest.swingui.relational.DPVRelationalSubView" name="From_LM_Introduction to the LDM - Financial collateral hierarchy" id="3B7238C7-F85E-053D-61AF-6165528E9143">
<createdBy>nuvolia</createdBy>
<modifiedBy>nuvolia</modifiedBy>
<createdTime>2025-02-24 08:53:47 UTC</createdTime>
<autoRoute>false</autoRoute>
<boxInbox>true</boxInbox>
<showLegend>false</showLegend>
<showLabels>false</showLabels>
<showRelAttributes>false</showRelAttributes>
<gridEnabled>false</gridEnabled>
<showGrid>false</showGrid>
<diagramColor>-1</diagramColor>
<display>false</display>
<generatorId>DE3E6345-6F07-FE98-C527-B740741FC315</generatorId>
<notation>1</notation>
<objectViews>
<OView class="oracle.dbtools.crest.swingui.relational.TVTable" oid="50899113-AA37-0D2C-B448-9B34A18B9C27" otype="Table" vid="458D7091-527A-C064-BE3C-FCD5D052143E">
<hideElementsInCurrentOnly>false</hideElementsInCurrentOnly>
<bounds x="0" y="210" width="228" height="114"/>
<generatorID>3A9353F3-A89E-C9FF-0ABE-B801172B3EB6</generatorID>
</OView>
<OView class="oracle.dbtools.crest.swingui.relational.TVTable" oid="50899113-AA37-0D2C-B448-9B34A18B9C27" otype="Table" vid="68F6C242-6FFB-7987-5A6E-417C4668B5D2" vnum="1">
<hideElementsInCurrentOnly>false</hideElementsInCurrentOnly>
<bounds x="233" y="210" width="167" height="128"/>
<generatorID>0108F510-E450-4900-23D9-08AB93F75E8F</generatorID>
</OView>
<OView class="oracle.dbtools.crest.swingui.relational.TVTable" oid="50899113-AA37-0D2C-B448-9B34A18B9C27" otype="Table" vid="A58D7D36-4F53-C67E-D6C6-D1768BE59B26" vnum="2">
<hideElementsInCurrentOnly>false</hideElementsInCurrentOnly>
<bounds x="496" y="2" width="350" height="156"/>
<generatorID>46E707AF-AAF6-1C83-9789-95CE99918C7D</generatorID>
</OView>
<OView class="oracle.dbtools.crest.swingui.relational.TVTable" oid="50899113-AA37-0D2C-B448-9B34A18B9C27" otype="Table" vid="2A3143CD-7080-63AB-10B7-AAB955E1798F" vnum="3">
<hideElementsInCurrentOnly>false</hideElementsInCurrentOnly>
<bounds x="406" y="210" width="316" height="156"/>
<generatorID>A3A9EA3A-C15C-2F1F-642D-99196344F6D3</generatorID>
</OView>
<OView class="oracle.dbtools.crest.swingui.relational.TVTable" oid="50899113-AA37-0D2C-B448-9B34A18B9C27" otype="Table" vid="16135660-9E6B-8875-FEA7-B967D49A1C84" vnum="4">
<hideElementsInCurrentOnly>false</hideElementsInCurrentOnly>
<bounds x="1242" y="210" width="316" height="128"/>
<generatorID>9661B553-3B65-9145-2DB5-92B013649E2F</generatorID>
</OView>
<OView class="oracle.dbtools.crest.swingui.relational.TVTable" oid="50899113-AA37-0D2C-B448-9B34A18B9C27" otype="Table" vid="462CABF2-E432-BC57-15EC-639AEAB195BC" vnum="5">
<hideElementsInCurrentOnly>false</hideElementsInCurrentOnly>
<bounds x="737" y="210" width="361" height="142"/>
<generatorID>2D96607B-AB20-6B08-54C7-FD35FFEEAECC</generatorID>
</OView>
<OView class="oracle.dbtools.crest.swingui.relational.TVTable" oid="50899113-AA37-0D2C-B448-9B34A18B9C27" otype="Table" vid="2D9118DC-C691-9EA0-F73B-2E070F58A3B8" vnum="6">
<hideElementsInCurrentOnly>false</hideElementsInCurrentOnly>
<bounds x="1109" y="210" width="128" height="100"/>
<generatorID>E4D01DCD-7F28-F480-B2BF-DFA48CD28C57</generatorID>
</OView>
<OView class="oracle.dbtools.crest.swingui.relational.TVTable" oid="D445DE24-2365-9185-D3B4-936ABF9EFA80" otype="Table" vid="8564A9A7-8CD4-9079-3780-EF696CA8FA2C">
<hideElementsInCurrentOnly>false</hideElementsInCurrentOnly>
<bounds x="0" y="0" width="303" height="178"/>
<generatorID>9FD8C198-070B-CA4F-5327-7F092C2BBCD5</generatorID>
</OView>
<OView class="oracle.dbtools.crest.swingui.relational.TVTable" oid="D445DE24-2365-9185-D3B4-936ABF9EFA80" otype="Table" vid="4F1421B1-29AD-6AAE-B4A1-C51DB0969B16" vnum="1">
<hideElementsInCurrentOnly>false</hideElementsInCurrentOnly>
<bounds x="1107" y="2" width="234" height="128"/>
<generatorID>414852F2-9F02-EB4D-7629-96B30D805C15</generatorID>
</OView>
</objectViews>
<connectors>
<Connector class="oracle.dbtools.crest.swingui.relational.TVFKRelation" oid="C731ECDA-0A31-E447-F7C4-3EAAB3B86EF6" otype="FKIndexAssociation" vid_source="8564A9A7-8CD4-9079-3780-EF696CA8FA2C" vid_target="458D7091-527A-C064-BE3C-FCD5D052143E">
<hideElementsInCurrentOnly>false</hideElementsInCurrentOnly>
<backgroundColor>-16777216</backgroundColor>
<lineWidth>1</lineWidth>
<points>
<point x="303" y="178"/>
<point x="228" y="268"/>
</points>
</Connector>
<Connector class="oracle.dbtools.crest.swingui.relational.TVFKRelation" oid="FADC11F8-5047-6E94-224B-961DB3D8B5DB" otype="FKIndexAssociation" vid_source="8564A9A7-8CD4-9079-3780-EF696CA8FA2C" vid_target="458D7091-527A-C064-BE3C-FCD5D052143E">
<hideElementsInCurrentOnly>false</hideElementsInCurrentOnly>
<backgroundColor>-16777216</backgroundColor>
<lineWidth>1</lineWidth>
<points>
<point x="303" y="178"/>
<point x="228" y="268"/>
</points>
</Connector>
</connectors>
</Diagram>
