<?xml version = '1.0' encoding = 'UTF-8'?>
<Diagram class="oracle.dbtools.crest.swingui.relational.DPVRelationalSubView" name="From_LM_5-Collateral given-received indicator" id="D6BDCEC8-9811-3A3F-B169-1C0649BF0ED3">
<createdBy>nuvolia</createdBy>
<modifiedBy>nuvolia</modifiedBy>
<createdTime>2025-02-24 08:53:46 UTC</createdTime>
<autoRoute>false</autoRoute>
<boxInbox>true</boxInbox>
<showLegend>false</showLegend>
<showLabels>false</showLabels>
<showRelAttributes>false</showRelAttributes>
<gridEnabled>false</gridEnabled>
<showGrid>false</showGrid>
<diagramColor>-1</diagramColor>
<display>false</display>
<generatorId>84ADF784-54EE-F64E-8AF9-53A4CCF8045F</generatorId>
<notation>1</notation>
<objectViews>
<OView class="oracle.dbtools.crest.swingui.relational.TVTable" oid="262B121A-C4D3-29A9-01F2-2BEDC56F243E" otype="Table" vid="100E049B-8DA0-F9D3-E022-4648188875A3">
<hideElementsInCurrentOnly>false</hideElementsInCurrentOnly>
<bounds x="1273" y="812" width="334" height="234"/>
<generatorID>E19583AB-338A-3461-39DA-551139DCC433</generatorID>
</OView>
<OView class="oracle.dbtools.crest.swingui.relational.TVTable" oid="2DE470E7-D7B9-C780-5868-0D608DD79667" otype="Table" vid="12536EB5-DB6B-154B-D33F-BB2E94401C54">
<hideElementsInCurrentOnly>false</hideElementsInCurrentOnly>
<bounds x="972" y="810" width="285" height="234"/>
<generatorID>D66A9D8A-2B3A-027B-6117-3A530F98E6B7</generatorID>
</OView>
<OView class="oracle.dbtools.crest.swingui.relational.TVTable" oid="50899113-AA37-0D2C-B448-9B34A18B9C27" otype="Table" vid="BA71AD4B-2889-4270-6D1B-61DA17009226">
<hideElementsInCurrentOnly>false</hideElementsInCurrentOnly>
<bounds x="1345" y="17" width="268" height="212"/>
<generatorID>6D2A9FD0-B15F-14EB-3F33-2154CB757F91</generatorID>
</OView>
<OView class="oracle.dbtools.crest.swingui.relational.TVTable" oid="61159193-89D0-2122-CEF0-0F7D2E2CAE76" otype="Table" vid="0AC32B7E-8611-E057-2EDF-569E2AEFDACB">
<hideElementsInCurrentOnly>false</hideElementsInCurrentOnly>
<bounds x="1988" y="17" width="334" height="164"/>
<generatorID>A7D9C95F-CDDF-7686-9B30-125DF1842C26</generatorID>
</OView>
<OView class="oracle.dbtools.crest.swingui.relational.TVTable" oid="76AD2825-5419-EF37-A2E2-C5F9EC220FFB" otype="Table" vid="275EAE88-FBDA-B448-239E-4A0259B75918">
<hideElementsInCurrentOnly>false</hideElementsInCurrentOnly>
<bounds x="2466" y="812" width="364" height="349"/>
<generatorID>B9366B18-3871-6575-D839-2964C69FEE3E</generatorID>
</OView>
<OView class="oracle.dbtools.crest.swingui.relational.TVTable" oid="8016CA18-C30B-99A8-6B2B-1C9D84F7283F" otype="Table" vid="CAB14BA2-0132-3832-7663-3D7ADB774680">
<hideElementsInCurrentOnly>false</hideElementsInCurrentOnly>
<bounds x="187" y="810" width="407" height="262"/>
<generatorID>F0AD3BFA-2905-D614-5332-F3AD8A932460</generatorID>
</OView>
<OView class="oracle.dbtools.crest.swingui.relational.TVTable" oid="8016CA18-C30B-99A8-6B2B-1C9D84F7283F" otype="Table" vid="E3AEC02D-901D-08B8-97CA-5FBB7BC0CBDB" vnum="1">
<hideElementsInCurrentOnly>false</hideElementsInCurrentOnly>
<bounds x="487" y="616" width="249" height="122"/>
<generatorID>E5F359A5-E7A1-5190-D34B-0733F691DEB5</generatorID>
</OView>
<OView class="oracle.dbtools.crest.swingui.relational.TVTable" oid="8016CA18-C30B-99A8-6B2B-1C9D84F7283F" otype="Table" vid="4202B017-85F5-E257-7E92-5F6BC2FD21B4" vnum="2">
<hideElementsInCurrentOnly>false</hideElementsInCurrentOnly>
<bounds x="627" y="810" width="330" height="234"/>
<generatorID>F518E542-F37E-46FB-C594-FF87C785BCC5</generatorID>
</OView>
<OView class="oracle.dbtools.crest.swingui.relational.TVTable" oid="8FB4C679-5B5A-3547-8128-77E6F027C567" otype="Table" vid="E828B998-C847-D566-0A94-5649AC432A31">
<hideElementsInCurrentOnly>false</hideElementsInCurrentOnly>
<bounds x="635" y="17" width="397" height="511"/>
<generatorID>1181C9BC-B308-6E4B-0555-A167962F1936</generatorID>
</OView>
<OView class="oracle.dbtools.crest.swingui.relational.TVTable" oid="A0AE0934-67E5-387C-093D-FD0A2475B55A" otype="Table" vid="714A7210-859C-2A00-F341-D126B38A7476">
<hideElementsInCurrentOnly>false</hideElementsInCurrentOnly>
<bounds x="1523" y="324" width="381" height="292"/>
<generatorID>04EDA913-C60B-FD88-49C8-D8829E858618</generatorID>
</OView>
<OView class="oracle.dbtools.crest.swingui.relational.TVTable" oid="A98EFD74-88DE-12CA-8E50-3AB92A1BB45A" otype="Table" vid="8F690F55-2910-4F76-0596-99B7198F2C09">
<hideElementsInCurrentOnly>false</hideElementsInCurrentOnly>
<bounds x="73" y="17" width="326" height="272"/>
<generatorID>F5AA96CB-B0EA-B96D-5718-D3C38F964D12</generatorID>
</OView>
<OView class="oracle.dbtools.crest.swingui.relational.TVTable" oid="ACB3A44F-4954-5E1C-6E1A-5913088493AE" otype="Table" vid="86F81E2C-2C39-02FC-71D4-CA8424A247F7">
<hideElementsInCurrentOnly>false</hideElementsInCurrentOnly>
<bounds x="2458" y="324" width="315" height="254"/>
<generatorID>4B3693ED-CA3B-F879-006C-5E79C4004152</generatorID>
</OView>
<OView class="oracle.dbtools.crest.swingui.relational.TVTable" oid="AFFC737C-7F4E-C5EF-2E8D-886FDADE7A9B" otype="Table" vid="ECABD082-E6AD-6849-579D-5ACBA0F96F80">
<hideElementsInCurrentOnly>false</hideElementsInCurrentOnly>
<bounds x="1975" y="526" width="197" height="86"/>
<generatorID>182901B1-0013-2A04-23A9-5C507A1E5451</generatorID>
</OView>
<OView class="oracle.dbtools.crest.swingui.relational.TVTable" oid="AFFC737C-7F4E-C5EF-2E8D-886FDADE7A9B" otype="Table" vid="9C88ED17-57A9-D081-0996-43D8957CB9CF" vnum="1">
<hideElementsInCurrentOnly>false</hideElementsInCurrentOnly>
<bounds x="2185" y="526" width="197" height="86"/>
<generatorID>96D2B434-4051-CC81-2EC0-4D341C4D1389</generatorID>
</OView>
<OView class="oracle.dbtools.crest.swingui.relational.TVTable" oid="AFFC737C-7F4E-C5EF-2E8D-886FDADE7A9B" otype="Table" vid="D6720E89-93F8-2700-458F-B7860E252C5E" vnum="2">
<hideElementsInCurrentOnly>false</hideElementsInCurrentOnly>
<bounds x="2001" y="324" width="334" height="142"/>
<generatorID>D0B4A33F-278F-D5B5-AD8C-C74B720DA4D2</generatorID>
</OView>
<OView class="oracle.dbtools.crest.swingui.relational.TVTable" oid="B47D2836-2131-1937-ED75-D91976FE89C8" otype="Table" vid="290E1001-26D9-4D00-B95C-F8BDFF2C9E2C">
<hideElementsInCurrentOnly>false</hideElementsInCurrentOnly>
<bounds x="113" y="324" width="271" height="146"/>
<generatorID>C770AA7B-639A-FB87-9B2A-0ABE1BEC9CBD</generatorID>
</OView>
<OView class="oracle.dbtools.crest.swingui.relational.TVTable" oid="B47D2836-2131-1937-ED75-D91976FE89C8" otype="Table" vid="FA73C08F-D6FD-AC08-5C66-C697683F7883" vnum="1">
<hideElementsInCurrentOnly>false</hideElementsInCurrentOnly>
<bounds x="12" y="616" width="283" height="118"/>
<generatorID>CD128606-E31A-1A73-1CF4-1FC439C7159D</generatorID>
</OView>
<OView class="oracle.dbtools.crest.swingui.relational.TVTable" oid="B47D2836-2131-1937-ED75-D91976FE89C8" otype="Table" vid="A2E3137D-4CD6-DABA-2708-FB8C08209BE8" vnum="2">
<hideElementsInCurrentOnly>false</hideElementsInCurrentOnly>
<bounds x="302" y="616" width="168" height="132"/>
<generatorID>D8D25781-AFAE-C2C0-AF33-3D5CCD909EC3</generatorID>
</OView>
<OView class="oracle.dbtools.crest.swingui.relational.TVTable" oid="C69E8830-3ABA-AB4A-CACE-BFA80ACD3E8B" otype="Table" vid="258410DA-7CE9-2E0D-4862-E3ECB4773457">
<hideElementsInCurrentOnly>false</hideElementsInCurrentOnly>
<bounds x="2059" y="812" width="399" height="336"/>
<generatorID>49574C04-2FDB-F652-8758-D2E244B85590</generatorID>
</OView>
<OView class="oracle.dbtools.crest.swingui.relational.TVTable" oid="D445DE24-2365-9185-D3B4-936ABF9EFA80" otype="Table" vid="606CAD33-AF75-EBFB-C9E9-BDA432273D1A">
<hideElementsInCurrentOnly>false</hideElementsInCurrentOnly>
<bounds x="2474" y="17" width="305" height="226"/>
<generatorID>A2D2B894-BE4E-224E-8884-46DCAC041AD4</generatorID>
</OView>
<OView class="oracle.dbtools.crest.swingui.relational.TVTable" oid="DD03AD3E-FB82-0F63-9C28-CCDF77BF42E2" otype="Table" vid="086D923C-3C3B-E5D6-2152-8320732F1881">
<hideElementsInCurrentOnly>false</hideElementsInCurrentOnly>
<bounds x="1618" y="812" width="428" height="254"/>
<generatorID>857A9BA5-77D7-A1CD-D415-45E00ADCE8B0</generatorID>
</OView>
<OView class="oracle.dbtools.crest.swingui.relational.TVTable" oid="DD7D1894-F444-47D7-9B0A-F7110D49C4BC" otype="Table" vid="5ED6A7E1-3870-D832-F979-9973342F1215">
<hideElementsInCurrentOnly>false</hideElementsInCurrentOnly>
<bounds x="1106" y="526" width="246" height="72"/>
<generatorID>7BAE3878-EF0E-B5F3-B423-3F0EB629FC71</generatorID>
</OView>
<OView class="oracle.dbtools.crest.swingui.relational.TVTable" oid="DD7D1894-F444-47D7-9B0A-F7110D49C4BC" otype="Table" vid="73ED5B94-9B5C-79E3-B569-A5948946BD35" vnum="1">
<hideElementsInCurrentOnly>false</hideElementsInCurrentOnly>
<bounds x="1362" y="526" width="113" height="100"/>
<generatorID>0E64D56F-BA21-0480-E3DB-558C77C1E076</generatorID>
</OView>
<OView class="oracle.dbtools.crest.swingui.relational.TVTable" oid="DD7D1894-F444-47D7-9B0A-F7110D49C4BC" otype="Table" vid="0F531C05-DCEF-F2CE-F973-DF67D59A1BEC" vnum="2">
<hideElementsInCurrentOnly>false</hideElementsInCurrentOnly>
<bounds x="1211" y="324" width="268" height="128"/>
<generatorID>583D8567-26E3-72F7-B99C-028A4E6BE72B</generatorID>
</OView>
</objectViews>
<connectors>
<Connector class="oracle.dbtools.crest.swingui.relational.TVFKRelation" oid="04E9566E-473F-CFE9-E421-DBBD18895DEB" otype="FKIndexAssociation" vid_source="5ED6A7E1-3870-D832-F979-9973342F1215" vid_target="12536EB5-DB6B-154B-D33F-BB2E94401C54">
<hideElementsInCurrentOnly>false</hideElementsInCurrentOnly>
<backgroundColor>-16777216</backgroundColor>
<lineWidth>1</lineWidth>
<points>
<point x="1352" y="598"/>
<point x="1257" y="924"/>
</points>
</Connector>
<Connector class="oracle.dbtools.crest.swingui.relational.TVFKRelation" oid="05EB3BA3-233A-92C8-F660-4A240A944B45" otype="FKIndexAssociation" vid_source="E828B998-C847-D566-0A94-5649AC432A31" vid_target="12536EB5-DB6B-154B-D33F-BB2E94401C54">
<hideElementsInCurrentOnly>false</hideElementsInCurrentOnly>
<backgroundColor>-16777216</backgroundColor>
<lineWidth>1</lineWidth>
<points>
<point x="1032" y="528"/>
<point x="1257" y="967"/>
</points>
</Connector>
<Connector class="oracle.dbtools.crest.swingui.relational.TVFKRelation" oid="09265C71-362F-844C-5844-76B2AB3B4A71" otype="FKIndexAssociation" vid_source="86F81E2C-2C39-02FC-71D4-CA8424A247F7" vid_target="086D923C-3C3B-E5D6-2152-8320732F1881">
<hideElementsInCurrentOnly>false</hideElementsInCurrentOnly>
<backgroundColor>-16777216</backgroundColor>
<lineWidth>1</lineWidth>
<points>
<point x="2773" y="464"/>
<point x="2046" y="1066"/>
</points>
</Connector>
<Connector class="oracle.dbtools.crest.swingui.relational.TVFKRelation" oid="145F3E1D-380F-B4B7-4573-226CAB970AFA" otype="FKIndexAssociation" vid_source="8F690F55-2910-4F76-0596-99B7198F2C09" vid_target="CAB14BA2-0132-3832-7663-3D7ADB774680">
<hideElementsInCurrentOnly>false</hideElementsInCurrentOnly>
<backgroundColor>-16777216</backgroundColor>
<lineWidth>1</lineWidth>
<points>
<point x="399" y="169"/>
<point x="594" y="1072"/>
</points>
</Connector>
<Connector class="oracle.dbtools.crest.swingui.relational.TVFKRelation" oid="19EB1FF3-4AB0-754A-65DC-A6D2AA25CB09" otype="FKIndexAssociation" vid_source="5ED6A7E1-3870-D832-F979-9973342F1215" vid_target="CAB14BA2-0132-3832-7663-3D7ADB774680">
<hideElementsInCurrentOnly>false</hideElementsInCurrentOnly>
<backgroundColor>-16777216</backgroundColor>
<lineWidth>1</lineWidth>
<points>
<point x="1352" y="598"/>
<point x="594" y="939"/>
</points>
</Connector>
<Connector class="oracle.dbtools.crest.swingui.relational.TVFKRelation" oid="2124CF8E-EC00-E29B-9CE5-EDF3F6140828" otype="FKIndexAssociation" vid_source="5ED6A7E1-3870-D832-F979-9973342F1215" vid_target="CAB14BA2-0132-3832-7663-3D7ADB774680">
<hideElementsInCurrentOnly>false</hideElementsInCurrentOnly>
<backgroundColor>-16777216</backgroundColor>
<lineWidth>1</lineWidth>
<points>
<point x="1352" y="598"/>
<point x="594" y="999"/>
</points>
</Connector>
<Connector class="oracle.dbtools.crest.swingui.relational.TVFKRelation" oid="2DB3DEF8-F39D-BC1A-6FA4-B7AF9944B61F" otype="FKIndexAssociation" vid_source="8F690F55-2910-4F76-0596-99B7198F2C09" vid_target="100E049B-8DA0-F9D3-E022-4648188875A3">
<hideElementsInCurrentOnly>false</hideElementsInCurrentOnly>
<backgroundColor>-16777216</backgroundColor>
<lineWidth>1</lineWidth>
<points>
<point x="399" y="289"/>
<point x="1607" y="914"/>
</points>
</Connector>
<Connector class="oracle.dbtools.crest.swingui.relational.TVFKRelation" oid="355871E3-7489-748D-4DF2-40FCBD6C0384" otype="FKIndexAssociation" vid_source="5ED6A7E1-3870-D832-F979-9973342F1215" vid_target="CAB14BA2-0132-3832-7663-3D7ADB774680">
<hideElementsInCurrentOnly>false</hideElementsInCurrentOnly>
<backgroundColor>-16777216</backgroundColor>
<lineWidth>1</lineWidth>
<points>
<point x="1352" y="598"/>
<point x="594" y="984"/>
</points>
</Connector>
<Connector class="oracle.dbtools.crest.swingui.relational.TVFKRelation" oid="3A3EADF5-65ED-864D-2969-F01F71C588A1" otype="FKIndexAssociation" vid_source="0AC32B7E-8611-E057-2EDF-569E2AEFDACB" vid_target="714A7210-859C-2A00-F341-D126B38A7476">
<hideElementsInCurrentOnly>false</hideElementsInCurrentOnly>
<backgroundColor>-16777216</backgroundColor>
<lineWidth>1</lineWidth>
<points>
<point x="2322" y="106"/>
<point x="1904" y="616"/>
</points>
</Connector>
<Connector class="oracle.dbtools.crest.swingui.relational.TVFKRelation" oid="466D50CD-DF01-14ED-CAC0-83DAC7BC7376" otype="FKIndexAssociation" vid_source="E828B998-C847-D566-0A94-5649AC432A31" vid_target="8F690F55-2910-4F76-0596-99B7198F2C09">
<hideElementsInCurrentOnly>false</hideElementsInCurrentOnly>
<backgroundColor>-16777216</backgroundColor>
<lineWidth>1</lineWidth>
<points>
<point x="1032" y="528"/>
<point x="399" y="157"/>
</points>
</Connector>
<Connector class="oracle.dbtools.crest.swingui.relational.TVFKRelation" oid="498EE545-0379-C536-81AB-89A0A761EA67" otype="FKIndexAssociation" vid_source="ECABD082-E6AD-6849-579D-5ACBA0F96F80" vid_target="275EAE88-FBDA-B448-239E-4A0259B75918">
<hideElementsInCurrentOnly>false</hideElementsInCurrentOnly>
<backgroundColor>-16777216</backgroundColor>
<lineWidth>1</lineWidth>
<points>
<point x="2172" y="576"/>
<point x="2830" y="1161"/>
</points>
</Connector>
<Connector class="oracle.dbtools.crest.swingui.relational.TVFKRelation" oid="589F0DEC-AC47-4FAA-8870-4F6A19AAE510" otype="FKIndexAssociation" vid_source="BA71AD4B-2889-4270-6D1B-61DA17009226" vid_target="714A7210-859C-2A00-F341-D126B38A7476">
<hideElementsInCurrentOnly>false</hideElementsInCurrentOnly>
<backgroundColor>-16777216</backgroundColor>
<lineWidth>1</lineWidth>
<points>
<point x="1613" y="128"/>
<point x="1904" y="616"/>
</points>
</Connector>
<Connector class="oracle.dbtools.crest.swingui.relational.TVFKRelation" oid="5D183E17-D2DD-73D0-261F-54380DB9FFB6" otype="FKIndexAssociation" vid_source="8F690F55-2910-4F76-0596-99B7198F2C09" vid_target="290E1001-26D9-4D00-B95C-F8BDFF2C9E2C">
<hideElementsInCurrentOnly>false</hideElementsInCurrentOnly>
<backgroundColor>-16777216</backgroundColor>
<lineWidth>1</lineWidth>
<points>
<point x="399" y="289"/>
<point x="384" y="399"/>
</points>
</Connector>
<Connector class="oracle.dbtools.crest.swingui.relational.TVFKRelation" oid="6264FF65-EA39-D0F2-816D-5813AD8A0FF5" otype="FKIndexAssociation" vid_source="BA71AD4B-2889-4270-6D1B-61DA17009226" vid_target="5ED6A7E1-3870-D832-F979-9973342F1215">
<hideElementsInCurrentOnly>false</hideElementsInCurrentOnly>
<backgroundColor>-16777216</backgroundColor>
<lineWidth>1</lineWidth>
<points>
<point x="1613" y="125"/>
<point x="1352" y="598"/>
</points>
</Connector>
<Connector class="oracle.dbtools.crest.swingui.relational.TVFKRelation" oid="732CE9FD-D1B2-DD06-8ED4-154CDC7936C0" otype="FKIndexAssociation" vid_source="8F690F55-2910-4F76-0596-99B7198F2C09" vid_target="CAB14BA2-0132-3832-7663-3D7ADB774680">
<hideElementsInCurrentOnly>false</hideElementsInCurrentOnly>
<backgroundColor>-16777216</backgroundColor>
<lineWidth>1</lineWidth>
<points>
<point x="399" y="169"/>
<point x="594" y="1072"/>
</points>
</Connector>
<Connector class="oracle.dbtools.crest.swingui.relational.TVFKRelation" oid="7685CA06-0D5A-C700-2DEB-5E5B5F120CC4" otype="FKIndexAssociation" vid_source="ECABD082-E6AD-6849-579D-5ACBA0F96F80" vid_target="086D923C-3C3B-E5D6-2152-8320732F1881">
<hideElementsInCurrentOnly>false</hideElementsInCurrentOnly>
<backgroundColor>-16777216</backgroundColor>
<lineWidth>1</lineWidth>
<points>
<point x="2172" y="577"/>
<point x="2046" y="1066"/>
</points>
</Connector>
<Connector class="oracle.dbtools.crest.swingui.relational.TVFKRelation" oid="9524F0DD-591F-1FFF-B5E4-9B3A85DA28E3" otype="FKIndexAssociation" vid_source="8F690F55-2910-4F76-0596-99B7198F2C09" vid_target="CAB14BA2-0132-3832-7663-3D7ADB774680">
<hideElementsInCurrentOnly>false</hideElementsInCurrentOnly>
<backgroundColor>-16777216</backgroundColor>
<lineWidth>1</lineWidth>
<points>
<point x="399" y="169"/>
<point x="594" y="1072"/>
</points>
</Connector>
<Connector class="oracle.dbtools.crest.swingui.relational.TVFKRelation" oid="994DE9EB-D086-8BF4-B456-334FAC38D58C" otype="FKIndexAssociation" vid_source="606CAD33-AF75-EBFB-C9E9-BDA432273D1A" vid_target="86F81E2C-2C39-02FC-71D4-CA8424A247F7">
<hideElementsInCurrentOnly>false</hideElementsInCurrentOnly>
<backgroundColor>-16777216</backgroundColor>
<lineWidth>1</lineWidth>
<points>
<point x="2779" y="243"/>
<point x="2773" y="451"/>
</points>
</Connector>
<Connector class="oracle.dbtools.crest.swingui.relational.TVFKRelation" oid="B4F11A80-A310-61D7-9B76-229FE3CF3573" otype="FKIndexAssociation" vid_source="ECABD082-E6AD-6849-579D-5ACBA0F96F80" vid_target="100E049B-8DA0-F9D3-E022-4648188875A3">
<hideElementsInCurrentOnly>false</hideElementsInCurrentOnly>
<backgroundColor>-16777216</backgroundColor>
<lineWidth>1</lineWidth>
<points>
<point x="2172" y="578"/>
<point x="1607" y="1046"/>
</points>
</Connector>
<Connector class="oracle.dbtools.crest.swingui.relational.TVFKRelation" oid="B519075A-9303-B1C4-4CB0-B964DC0308DE" otype="FKIndexAssociation" vid_source="0AC32B7E-8611-E057-2EDF-569E2AEFDACB" vid_target="ECABD082-E6AD-6849-579D-5ACBA0F96F80">
<hideElementsInCurrentOnly>false</hideElementsInCurrentOnly>
<backgroundColor>-16777216</backgroundColor>
<lineWidth>1</lineWidth>
<points>
<point x="2322" y="181"/>
<point x="2172" y="554"/>
</points>
</Connector>
<Connector class="oracle.dbtools.crest.swingui.relational.TVFKRelation" oid="B7370B16-B627-A350-5391-923AF4ECC492" otype="FKIndexAssociation" vid_source="ECABD082-E6AD-6849-579D-5ACBA0F96F80" vid_target="100E049B-8DA0-F9D3-E022-4648188875A3">
<hideElementsInCurrentOnly>false</hideElementsInCurrentOnly>
<backgroundColor>-16777216</backgroundColor>
<lineWidth>1</lineWidth>
<points>
<point x="2172" y="578"/>
<point x="1607" y="1046"/>
</points>
</Connector>
<Connector class="oracle.dbtools.crest.swingui.relational.TVFKRelation" oid="C731ECDA-0A31-E447-F7C4-3EAAB3B86EF6" otype="FKIndexAssociation" vid_source="606CAD33-AF75-EBFB-C9E9-BDA432273D1A" vid_target="BA71AD4B-2889-4270-6D1B-61DA17009226">
<hideElementsInCurrentOnly>false</hideElementsInCurrentOnly>
<backgroundColor>-16777216</backgroundColor>
<lineWidth>1</lineWidth>
<points>
<point x="2779" y="243"/>
<point x="1613" y="124"/>
</points>
</Connector>
<Connector class="oracle.dbtools.crest.swingui.relational.TVFKRelation" oid="E5578E01-7333-D5DD-F4D6-0785F5CE5C82" otype="FKIndexAssociation" vid_source="5ED6A7E1-3870-D832-F979-9973342F1215" vid_target="CAB14BA2-0132-3832-7663-3D7ADB774680">
<hideElementsInCurrentOnly>false</hideElementsInCurrentOnly>
<backgroundColor>-16777216</backgroundColor>
<lineWidth>1</lineWidth>
<points>
<point x="1352" y="598"/>
<point x="594" y="969"/>
</points>
</Connector>
<Connector class="oracle.dbtools.crest.swingui.relational.TVFKRelation" oid="E60F0737-1028-D550-35DE-84FF4B64A440" otype="FKIndexAssociation" vid_source="5ED6A7E1-3870-D832-F979-9973342F1215" vid_target="258410DA-7CE9-2E0D-4862-E3ECB4773457">
<hideElementsInCurrentOnly>false</hideElementsInCurrentOnly>
<backgroundColor>-16777216</backgroundColor>
<lineWidth>1</lineWidth>
<points>
<point x="1352" y="598"/>
<point x="2458" y="909"/>
</points>
</Connector>
<Connector class="oracle.dbtools.crest.swingui.relational.TVFKRelation" oid="E9DA167F-7228-A473-0071-F64C4901C8D5" otype="FKIndexAssociation" vid_source="8F690F55-2910-4F76-0596-99B7198F2C09" vid_target="100E049B-8DA0-F9D3-E022-4648188875A3">
<hideElementsInCurrentOnly>false</hideElementsInCurrentOnly>
<backgroundColor>-16777216</backgroundColor>
<lineWidth>1</lineWidth>
<points>
<point x="399" y="289"/>
<point x="1607" y="944"/>
</points>
</Connector>
<Connector class="oracle.dbtools.crest.swingui.relational.TVFKRelation" oid="EE1E3C0A-8A2F-B86B-7F04-F91ABA2BF088" otype="FKIndexAssociation" vid_source="0AC32B7E-8611-E057-2EDF-569E2AEFDACB" vid_target="BA71AD4B-2889-4270-6D1B-61DA17009226">
<hideElementsInCurrentOnly>false</hideElementsInCurrentOnly>
<backgroundColor>-16777216</backgroundColor>
<lineWidth>1</lineWidth>
<points>
<point x="2322" y="181"/>
<point x="1613" y="110"/>
</points>
</Connector>
<Connector class="oracle.dbtools.crest.swingui.relational.TVFKRelation" oid="F4BCE4F0-C665-D5F3-AB3D-F249E27820D5" otype="FKIndexAssociation" vid_source="8F690F55-2910-4F76-0596-99B7198F2C09" vid_target="CAB14BA2-0132-3832-7663-3D7ADB774680">
<hideElementsInCurrentOnly>false</hideElementsInCurrentOnly>
<backgroundColor>-16777216</backgroundColor>
<lineWidth>1</lineWidth>
<points>
<point x="399" y="169"/>
<point x="594" y="1072"/>
</points>
</Connector>
<Connector class="oracle.dbtools.crest.swingui.relational.TVFKRelation" oid="FADC11F8-5047-6E94-224B-961DB3D8B5DB" otype="FKIndexAssociation" vid_source="606CAD33-AF75-EBFB-C9E9-BDA432273D1A" vid_target="BA71AD4B-2889-4270-6D1B-61DA17009226">
<hideElementsInCurrentOnly>false</hideElementsInCurrentOnly>
<backgroundColor>-16777216</backgroundColor>
<lineWidth>1</lineWidth>
<points>
<point x="2779" y="243"/>
<point x="1613" y="124"/>
</points>
</Connector>
</connectors>
</Diagram>
