<?xml version = '1.0' encoding = 'UTF-8'?>
<Diagram class="oracle.dbtools.crest.swingui.relational.DPVRelationalSubView" name="From_LM_477-ae-requirements-security-collateral-received-re-used" id="DBC6B1DD-C7F2-ACF3-6EEA-A83B7F238E65">
<createdBy>nuvolia</createdBy>
<modifiedBy>nuvolia</modifiedBy>
<createdTime>2025-02-24 08:53:46 UTC</createdTime>
<autoRoute>false</autoRoute>
<boxInbox>true</boxInbox>
<showLegend>false</showLegend>
<showLabels>false</showLabels>
<showRelAttributes>false</showRelAttributes>
<gridEnabled>false</gridEnabled>
<showGrid>false</showGrid>
<diagramColor>-1</diagramColor>
<display>false</display>
<generatorId>D36F4DF8-616B-31BD-9964-41E5A378C33C</generatorId>
<notation>1</notation>
<objectViews>
<OView class="oracle.dbtools.crest.swingui.relational.TVTable" oid="2D314ED6-36F5-1E25-545B-E4048A011096" otype="Table" vid="07CDA730-1F82-56CC-576D-E94FE8FE35FA">
<hideElementsInCurrentOnly>false</hideElementsInCurrentOnly>
<bounds x="392" y="1056" width="138" height="114"/>
<generatorID>BB6B9C01-5415-537D-DD51-91D351EC787A</generatorID>
</OView>
<OView class="oracle.dbtools.crest.swingui.relational.TVTable" oid="2D314ED6-36F5-1E25-545B-E4048A011096" otype="Table" vid="5E745217-9309-F7EF-ECC0-FBC64CAFF28E" vnum="1">
<hideElementsInCurrentOnly>false</hideElementsInCurrentOnly>
<bounds x="22" y="1056" width="156" height="114"/>
<generatorID>FB9B49B3-F0B2-78F5-3C59-201BC533E704</generatorID>
</OView>
<OView class="oracle.dbtools.crest.swingui.relational.TVTable" oid="2D314ED6-36F5-1E25-545B-E4048A011096" otype="Table" vid="F99E87D6-7085-408F-AF99-C5FCAC328B86" vnum="2">
<hideElementsInCurrentOnly>false</hideElementsInCurrentOnly>
<bounds x="22" y="886" width="203" height="142"/>
<generatorID>0A4D5315-A86C-A499-FCB9-2E6E88708E5D</generatorID>
</OView>
<OView class="oracle.dbtools.crest.swingui.relational.TVTable" oid="2D314ED6-36F5-1E25-545B-E4048A011096" otype="Table" vid="5814D7AB-7ECE-4EF0-F994-1101AFDC4B3A" vnum="3">
<hideElementsInCurrentOnly>false</hideElementsInCurrentOnly>
<bounds x="192" y="1056" width="191" height="91"/>
<generatorID>DAE97122-95F3-53E1-DA7B-19195AB2B6EC</generatorID>
</OView>
<OView class="oracle.dbtools.crest.swingui.relational.TVTable" oid="2D314ED6-36F5-1E25-545B-E4048A011096" otype="Table" vid="5033958F-3B2D-F446-653F-A1464E9F1FCF" vnum="4">
<hideElementsInCurrentOnly>false</hideElementsInCurrentOnly>
<bounds x="262" y="886" width="356" height="100"/>
<generatorID>619E024E-3520-943C-390F-93681D4CF318</generatorID>
</OView>
<OView class="oracle.dbtools.crest.swingui.relational.TVTable" oid="2D314ED6-36F5-1E25-545B-E4048A011096" otype="Table" vid="02ADAEE5-3D99-F7FE-715B-0F893C2CF3E6" vnum="5">
<hideElementsInCurrentOnly>false</hideElementsInCurrentOnly>
<bounds x="82" y="666" width="332" height="156"/>
<generatorID>F1E54828-60E2-B774-4389-1C0F3196FA4D</generatorID>
</OView>
<OView class="oracle.dbtools.crest.swingui.relational.TVTable" oid="3B0DA3A3-81EF-617C-F874-529C4717941B" otype="Table" vid="2D1F215D-D879-5E41-AFA8-19059E512F19">
<hideElementsInCurrentOnly>false</hideElementsInCurrentOnly>
<bounds x="412" y="1486" width="418" height="86"/>
<generatorID>6AADE4E7-7A1A-125A-1846-A74ACE91382B</generatorID>
</OView>
<OView class="oracle.dbtools.crest.swingui.relational.TVTable" oid="3B0DA3A3-81EF-617C-F874-529C4717941B" otype="Table" vid="D8CEB484-C9BF-7760-9644-0F8EC4CDCCC1" vnum="1">
<hideElementsInCurrentOnly>false</hideElementsInCurrentOnly>
<bounds x="12" y="1486" width="373" height="86"/>
<generatorID>CF043BFD-697A-D36C-6705-10E4749B5484</generatorID>
</OView>
<OView class="oracle.dbtools.crest.swingui.relational.TVTable" oid="3B0DA3A3-81EF-617C-F874-529C4717941B" otype="Table" vid="3CF3D5A5-7C3A-1E54-658F-F90FF9DCCAEC" vnum="2">
<hideElementsInCurrentOnly>false</hideElementsInCurrentOnly>
<bounds x="202" y="1206" width="398" height="226"/>
<generatorID>92AB5149-53A6-60E5-AFC5-50FFBBE8B0F7</generatorID>
</OView>
<OView class="oracle.dbtools.crest.swingui.relational.TVTable" oid="50899113-AA37-0D2C-B448-9B34A18B9C27" otype="Table" vid="76352B5B-D009-71DD-4D90-1A4218A36E43">
<hideElementsInCurrentOnly>false</hideElementsInCurrentOnly>
<bounds x="1379" y="21" width="350" height="156"/>
<generatorID>E2C26C27-753E-7AD3-C733-1389207FFA26</generatorID>
</OView>
<OView class="oracle.dbtools.crest.swingui.relational.TVTable" oid="50899113-AA37-0D2C-B448-9B34A18B9C27" otype="Table" vid="3B1CDDE5-C5F6-24E6-52AE-04723A575802" vnum="1">
<hideElementsInCurrentOnly>false</hideElementsInCurrentOnly>
<bounds x="1289" y="331" width="316" height="156"/>
<generatorID>F05C818A-47AF-02F3-BE9E-A4FBBF03F8ED</generatorID>
</OView>
<OView class="oracle.dbtools.crest.swingui.relational.TVTable" oid="50899113-AA37-0D2C-B448-9B34A18B9C27" otype="Table" vid="DD4B08A0-BE3B-3465-BD1E-E55E2CB7E936" vnum="2">
<hideElementsInCurrentOnly>false</hideElementsInCurrentOnly>
<bounds x="1609" y="331" width="361" height="142"/>
<generatorID>218779A7-7FE2-4B25-1845-21184C590C88</generatorID>
</OView>
<OView class="oracle.dbtools.crest.swingui.relational.TVTable" oid="6B1E419F-DA82-318E-62C5-4497EF76FAF2" otype="Table" vid="5C74B328-A7F6-F336-5A47-D6791FF45F8E">
<hideElementsInCurrentOnly>false</hideElementsInCurrentOnly>
<bounds x="1179" y="1206" width="425" height="212"/>
<generatorID>6E49C847-302E-7063-98AE-7E796639C9CF</generatorID>
</OView>
<OView class="oracle.dbtools.crest.swingui.relational.TVTable" oid="A98EFD74-88DE-12CA-8E50-3AB92A1BB45A" otype="Table" vid="26A2B663-33B9-8DB1-978F-2229C2DFEDA0">
<hideElementsInCurrentOnly>false</hideElementsInCurrentOnly>
<bounds x="12" y="331" width="471" height="281"/>
<generatorID>64A0FD92-AE7B-E724-998F-6DDD9DB543FA</generatorID>
</OView>
<OView class="oracle.dbtools.crest.swingui.relational.TVTable" oid="A98EFD74-88DE-12CA-8E50-3AB92A1BB45A" otype="Table" vid="E05A201D-1B51-D80A-74FC-1F0720607821" vnum="1">
<hideElementsInCurrentOnly>false</hideElementsInCurrentOnly>
<bounds x="385" y="21" width="242" height="254"/>
<generatorID>936EA51F-25E2-0BC3-107A-5671DE898CC9</generatorID>
</OView>
<OView class="oracle.dbtools.crest.swingui.relational.TVTable" oid="A98EFD74-88DE-12CA-8E50-3AB92A1BB45A" otype="Table" vid="E155F412-C51A-64A8-1165-D5E56EE696EF" vnum="2">
<hideElementsInCurrentOnly>false</hideElementsInCurrentOnly>
<bounds x="506" y="331" width="298" height="100"/>
<generatorID>F2DA8775-B90E-AADD-AC73-D53903D6279D</generatorID>
</OView>
<OView class="oracle.dbtools.crest.swingui.relational.TVTable" oid="C632525F-A3D6-4846-3313-0EB97D72E175" otype="Table" vid="18124F6F-1A2B-D37D-DD6E-E5F518625549">
<hideElementsInCurrentOnly>false</hideElementsInCurrentOnly>
<bounds x="646" y="666" width="425" height="128"/>
<generatorID>2FF282A7-1E56-0A19-EAD6-C00FDE60B2AB</generatorID>
</OView>
<OView class="oracle.dbtools.crest.swingui.relational.TVTable" oid="C632525F-A3D6-4846-3313-0EB97D72E175" otype="Table" vid="38824983-D979-9A93-15F0-53132DED3599" vnum="1">
<hideElementsInCurrentOnly>false</hideElementsInCurrentOnly>
<bounds x="1097" y="886" width="220" height="100"/>
<generatorID>4DBD6A74-FDEF-863D-BD9C-4E0DC4B7E69D</generatorID>
</OView>
<OView class="oracle.dbtools.crest.swingui.relational.TVTable" oid="C632525F-A3D6-4846-3313-0EB97D72E175" otype="Table" vid="B39B52E9-A28A-73EC-0DFA-BEC1D0246A84" vnum="2">
<hideElementsInCurrentOnly>false</hideElementsInCurrentOnly>
<bounds x="826" y="331" width="434" height="100"/>
<generatorID>66C69FA0-68EA-8C55-6681-32AB845B6F65</generatorID>
</OView>
<OView class="oracle.dbtools.crest.swingui.relational.TVTable" oid="C632525F-A3D6-4846-3313-0EB97D72E175" otype="Table" vid="25B92DFE-8A16-0484-3B92-D411279D905A" vnum="3">
<hideElementsInCurrentOnly>false</hideElementsInCurrentOnly>
<bounds x="1096" y="666" width="425" height="156"/>
<generatorID>1EDB5D1C-6093-D5FE-0BBE-7DCB2E89A44F</generatorID>
</OView>
<OView class="oracle.dbtools.crest.swingui.relational.TVTable" oid="C632525F-A3D6-4846-3313-0EB97D72E175" otype="Table" vid="CE9C109A-AC17-EC74-5AB0-D17C17863110" vnum="4">
<hideElementsInCurrentOnly>false</hideElementsInCurrentOnly>
<bounds x="1339" y="886" width="171" height="114"/>
<generatorID>3ED16B48-DFC2-3FBB-070D-56B41896783C</generatorID>
</OView>
<OView class="oracle.dbtools.crest.swingui.relational.TVTable" oid="D445DE24-2365-9185-D3B4-936ABF9EFA80" otype="Table" vid="39F50BA0-AD2A-10A1-A69C-B2EDE83EF7C2">
<hideElementsInCurrentOnly>false</hideElementsInCurrentOnly>
<bounds x="1778" y="21" width="271" height="226"/>
<generatorID>871B46C8-3CEE-2652-7DCA-4F3AAF846028</generatorID>
</OView>
<OView class="oracle.dbtools.crest.swingui.relational.TVTable" oid="D4D4366C-FA9B-FFF5-A8F0-05AA6617CFE1" otype="Table" vid="4C62D363-DE88-5A9F-B60D-4717ECBE924C">
<hideElementsInCurrentOnly>false</hideElementsInCurrentOnly>
<bounds x="746" y="1206" width="425" height="226"/>
<generatorID>B87F90D9-0BA3-206C-68B5-7CF6294BD7C5</generatorID>
</OView>
<OView class="oracle.dbtools.crest.swingui.relational.TVTable" oid="FE5245B8-82D8-7EFF-2182-B3EE3F35AE26" otype="Table" vid="1D935475-5888-A148-C04A-495695652006">
<hideElementsInCurrentOnly>false</hideElementsInCurrentOnly>
<bounds x="1616" y="1206" width="425" height="212"/>
<generatorID>72C9DDFD-410E-5141-9B9B-D0F7A43A59C7</generatorID>
</OView>
</objectViews>
<connectors>
<Connector class="oracle.dbtools.crest.swingui.relational.TVFKRelation" oid="22935B72-A4DE-080B-FB4B-5F69210CFF1A" otype="FKIndexAssociation" vid_source="26A2B663-33B9-8DB1-978F-2229C2DFEDA0" vid_target="07CDA730-1F82-56CC-576D-E94FE8FE35FA">
<hideElementsInCurrentOnly>false</hideElementsInCurrentOnly>
<backgroundColor>-16777216</backgroundColor>
<lineWidth>1</lineWidth>
<points>
<point x="483" y="486"/>
<point x="530" y="1170"/>
</points>
</Connector>
<Connector class="oracle.dbtools.crest.swingui.relational.TVFKRelation" oid="3216A280-120C-B13D-43BB-C92B98579C73" otype="FKIndexAssociation" vid_source="26A2B663-33B9-8DB1-978F-2229C2DFEDA0" vid_target="18124F6F-1A2B-D37D-DD6E-E5F518625549">
<hideElementsInCurrentOnly>false</hideElementsInCurrentOnly>
<backgroundColor>-16777216</backgroundColor>
<lineWidth>1</lineWidth>
<points>
<point x="483" y="612"/>
<point x="1071" y="731"/>
</points>
</Connector>
<Connector class="oracle.dbtools.crest.swingui.relational.TVFKRelation" oid="634F7EFE-4235-1C0C-0876-5B4004780165" otype="FKIndexAssociation" vid_source="76352B5B-D009-71DD-4D90-1A4218A36E43" vid_target="2D1F215D-D879-5E41-AFA8-19059E512F19">
<hideElementsInCurrentOnly>false</hideElementsInCurrentOnly>
<backgroundColor>-16777216</backgroundColor>
<lineWidth>1</lineWidth>
<points>
<point x="1729" y="177"/>
<point x="830" y="1539"/>
</points>
</Connector>
<Connector class="oracle.dbtools.crest.swingui.relational.TVFKRelation" oid="64E45B6C-FFC3-2C60-38E5-68481B220CB8" otype="FKIndexAssociation" vid_source="26A2B663-33B9-8DB1-978F-2229C2DFEDA0" vid_target="18124F6F-1A2B-D37D-DD6E-E5F518625549">
<hideElementsInCurrentOnly>false</hideElementsInCurrentOnly>
<backgroundColor>-16777216</backgroundColor>
<lineWidth>1</lineWidth>
<points>
<point x="483" y="612"/>
<point x="1071" y="731"/>
</points>
</Connector>
<Connector class="oracle.dbtools.crest.swingui.relational.TVFKRelation" oid="6A77EB4A-3ED2-BD63-F54F-0CAE18EFDD43" otype="FKIndexAssociation" vid_source="26A2B663-33B9-8DB1-978F-2229C2DFEDA0" vid_target="07CDA730-1F82-56CC-576D-E94FE8FE35FA">
<hideElementsInCurrentOnly>false</hideElementsInCurrentOnly>
<backgroundColor>-16777216</backgroundColor>
<lineWidth>1</lineWidth>
<points>
<point x="483" y="486"/>
<point x="530" y="1170"/>
</points>
</Connector>
<Connector class="oracle.dbtools.crest.swingui.relational.TVFKRelation" oid="6D6EFA86-9481-58F5-49ED-CD09A5A0CACD" otype="FKIndexAssociation" vid_source="26A2B663-33B9-8DB1-978F-2229C2DFEDA0" vid_target="07CDA730-1F82-56CC-576D-E94FE8FE35FA">
<hideElementsInCurrentOnly>false</hideElementsInCurrentOnly>
<backgroundColor>-16777216</backgroundColor>
<lineWidth>1</lineWidth>
<points>
<point x="483" y="486"/>
<point x="530" y="1170"/>
</points>
</Connector>
<Connector class="oracle.dbtools.crest.swingui.relational.TVFKRelation" oid="83670F5B-33BA-074C-EBD1-2BE17104F7FF" otype="FKIndexAssociation" vid_source="76352B5B-D009-71DD-4D90-1A4218A36E43" vid_target="4C62D363-DE88-5A9F-B60D-4717ECBE924C">
<hideElementsInCurrentOnly>false</hideElementsInCurrentOnly>
<backgroundColor>-16777216</backgroundColor>
<lineWidth>1</lineWidth>
<points>
<point x="1729" y="126"/>
<point x="1171" y="1432"/>
</points>
</Connector>
<Connector class="oracle.dbtools.crest.swingui.relational.TVFKRelation" oid="88E7FC91-D9B1-B634-0BC9-16701B1147FF" otype="FKIndexAssociation" vid_source="18124F6F-1A2B-D37D-DD6E-E5F518625549" vid_target="1D935475-5888-A148-C04A-495695652006">
<hideElementsInCurrentOnly>false</hideElementsInCurrentOnly>
<backgroundColor>-16777216</backgroundColor>
<lineWidth>1</lineWidth>
<points>
<point x="1071" y="755"/>
<point x="2041" y="1418"/>
</points>
</Connector>
<Connector class="oracle.dbtools.crest.swingui.relational.TVFKRelation" oid="95696818-0507-86A0-D132-7FF0B50F3907" otype="FKIndexAssociation" vid_source="26A2B663-33B9-8DB1-978F-2229C2DFEDA0" vid_target="18124F6F-1A2B-D37D-DD6E-E5F518625549">
<hideElementsInCurrentOnly>false</hideElementsInCurrentOnly>
<backgroundColor>-16777216</backgroundColor>
<lineWidth>1</lineWidth>
<points>
<point x="483" y="612"/>
<point x="1071" y="731"/>
</points>
</Connector>
<Connector class="oracle.dbtools.crest.swingui.relational.TVFKRelation" oid="B64A4B45-AF79-EEAD-2309-6A3B3D767BB6" otype="FKIndexAssociation" vid_source="18124F6F-1A2B-D37D-DD6E-E5F518625549" vid_target="4C62D363-DE88-5A9F-B60D-4717ECBE924C">
<hideElementsInCurrentOnly>false</hideElementsInCurrentOnly>
<backgroundColor>-16777216</backgroundColor>
<lineWidth>1</lineWidth>
<points>
<point x="1071" y="756"/>
<point x="1171" y="1432"/>
</points>
</Connector>
<Connector class="oracle.dbtools.crest.swingui.relational.TVFKRelation" oid="C410C97C-F12C-4D85-8AEE-EC695DA4A4B6" otype="FKIndexAssociation" vid_source="76352B5B-D009-71DD-4D90-1A4218A36E43" vid_target="5C74B328-A7F6-F336-5A47-D6791FF45F8E">
<hideElementsInCurrentOnly>false</hideElementsInCurrentOnly>
<backgroundColor>-16777216</backgroundColor>
<lineWidth>1</lineWidth>
<points>
<point x="1729" y="177"/>
<point x="1604" y="1308"/>
</points>
</Connector>
<Connector class="oracle.dbtools.crest.swingui.relational.TVFKRelation" oid="C4C46D8C-E88F-45E7-B33B-BB7B5C6D7285" otype="FKIndexAssociation" vid_source="18124F6F-1A2B-D37D-DD6E-E5F518625549" vid_target="5C74B328-A7F6-F336-5A47-D6791FF45F8E">
<hideElementsInCurrentOnly>false</hideElementsInCurrentOnly>
<backgroundColor>-16777216</backgroundColor>
<lineWidth>1</lineWidth>
<points>
<point x="1071" y="755"/>
<point x="1604" y="1418"/>
</points>
</Connector>
<Connector class="oracle.dbtools.crest.swingui.relational.TVFKRelation" oid="C731ECDA-0A31-E447-F7C4-3EAAB3B86EF6" otype="FKIndexAssociation" vid_source="39F50BA0-AD2A-10A1-A69C-B2EDE83EF7C2" vid_target="76352B5B-D009-71DD-4D90-1A4218A36E43">
<hideElementsInCurrentOnly>false</hideElementsInCurrentOnly>
<backgroundColor>-16777216</backgroundColor>
<lineWidth>1</lineWidth>
<points>
<point x="2049" y="136"/>
<point x="1729" y="177"/>
</points>
</Connector>
<Connector class="oracle.dbtools.crest.swingui.relational.TVFKRelation" oid="E76A17E1-5C5B-E9AE-D300-BF3B0415C214" otype="FKIndexAssociation" vid_source="39F50BA0-AD2A-10A1-A69C-B2EDE83EF7C2" vid_target="1D935475-5888-A148-C04A-495695652006">
<hideElementsInCurrentOnly>false</hideElementsInCurrentOnly>
<backgroundColor>-16777216</backgroundColor>
<lineWidth>1</lineWidth>
<points>
<point x="2049" y="154"/>
<point x="2041" y="1418"/>
</points>
</Connector>
<Connector class="oracle.dbtools.crest.swingui.relational.TVFKRelation" oid="EF1C9349-7A18-7456-3549-7B8BF2B93F22" otype="FKIndexAssociation" vid_source="07CDA730-1F82-56CC-576D-E94FE8FE35FA" vid_target="2D1F215D-D879-5E41-AFA8-19059E512F19">
<hideElementsInCurrentOnly>false</hideElementsInCurrentOnly>
<backgroundColor>-16777216</backgroundColor>
<lineWidth>1</lineWidth>
<points>
<point x="530" y="1170"/>
<point x="830" y="1531"/>
</points>
</Connector>
<Connector class="oracle.dbtools.crest.swingui.relational.TVFKRelation" oid="FADC11F8-5047-6E94-224B-961DB3D8B5DB" otype="FKIndexAssociation" vid_source="39F50BA0-AD2A-10A1-A69C-B2EDE83EF7C2" vid_target="76352B5B-D009-71DD-4D90-1A4218A36E43">
<hideElementsInCurrentOnly>false</hideElementsInCurrentOnly>
<backgroundColor>-16777216</backgroundColor>
<lineWidth>1</lineWidth>
<points>
<point x="2049" y="136"/>
<point x="1729" y="177"/>
</points>
</Connector>
</connectors>
</Diagram>
