<?xml version = '1.0' encoding = 'UTF-8'?>
<Diagram class="oracle.dbtools.crest.swingui.relational.DPVRelationalSubView" name="From_LM_Introduction to the LDM - Syndicated and sub-participation loans" id="DF820D46-0E82-0868-7A71-855E6AB52A1D">
<createdBy>nuvolia</createdBy>
<modifiedBy>nuvolia</modifiedBy>
<createdTime>2025-02-24 08:53:47 UTC</createdTime>
<autoRoute>false</autoRoute>
<boxInbox>true</boxInbox>
<showLegend>false</showLegend>
<showLabels>false</showLabels>
<showRelAttributes>false</showRelAttributes>
<gridEnabled>false</gridEnabled>
<showGrid>false</showGrid>
<diagramColor>-1</diagramColor>
<display>false</display>
<generatorId>26E986E3-C151-0807-D15F-4F84392FD4BA</generatorId>
<notation>1</notation>
<objectViews>
<OView class="oracle.dbtools.crest.swingui.relational.TVTable" oid="19A49ADC-7733-C7D1-45F1-2669DC3CBAA0" otype="Table" vid="D404A8A7-4CFC-CE33-8043-6CF58B8D2807">
<hideElementsInCurrentOnly>false</hideElementsInCurrentOnly>
<bounds x="766" y="20" width="158" height="96"/>
<generatorID>E81E26F9-C714-71E2-342B-EC86A1C07269</generatorID>
</OView>
<OView class="oracle.dbtools.crest.swingui.relational.TVTable" oid="19A49ADC-7733-C7D1-45F1-2669DC3CBAA0" otype="Table" vid="CBEC90FA-F127-ADF3-969A-59D9C300CD4C" vnum="1">
<hideElementsInCurrentOnly>false</hideElementsInCurrentOnly>
<bounds x="950" y="190" width="255" height="68"/>
<generatorID>9AB5D86B-E795-DAFA-F1C0-C3BEB8144051</generatorID>
</OView>
<OView class="oracle.dbtools.crest.swingui.relational.TVTable" oid="19A49ADC-7733-C7D1-45F1-2669DC3CBAA0" otype="Table" vid="84A7237C-9756-165A-DE27-86AFBB0523EF" vnum="2">
<hideElementsInCurrentOnly>false</hideElementsInCurrentOnly>
<bounds x="749" y="190" width="189" height="68"/>
<generatorID>6B7CB334-1EAD-2B42-51FE-0C61D853533B</generatorID>
</OView>
<OView class="oracle.dbtools.crest.swingui.relational.TVTable" oid="3EF1F407-7F5B-B1A6-A591-776EAA3FE0F4" otype="Table" vid="F3EBC20E-1F04-413B-D858-A5EE13626F3C">
<hideElementsInCurrentOnly>false</hideElementsInCurrentOnly>
<bounds x="7" y="20" width="142" height="166"/>
<generatorID>7A36F649-EC48-CE1A-49EF-459739D4A5F7</generatorID>
</OView>
<OView class="oracle.dbtools.crest.swingui.relational.TVTable" oid="A98EFD74-88DE-12CA-8E50-3AB92A1BB45A" otype="Table" vid="1428A2AD-0015-9D25-E352-292308B64C3B">
<hideElementsInCurrentOnly>false</hideElementsInCurrentOnly>
<bounds x="238" y="320" width="265" height="82"/>
<generatorID>BFF83588-D676-1DCF-1687-080182A8219C</generatorID>
</OView>
<OView class="oracle.dbtools.crest.swingui.relational.TVTable" oid="A98EFD74-88DE-12CA-8E50-3AB92A1BB45A" otype="Table" vid="C5503273-8D75-43D8-A86D-7EC8E9244D3B" vnum="1">
<hideElementsInCurrentOnly>false</hideElementsInCurrentOnly>
<bounds x="510" y="190" width="230" height="111"/>
<generatorID>3C92BEB7-F2E3-036E-C691-3EBBC1F89298</generatorID>
</OView>
<OView class="oracle.dbtools.crest.swingui.relational.TVTable" oid="A98EFD74-88DE-12CA-8E50-3AB92A1BB45A" otype="Table" vid="B4326883-AA66-EA6C-13BF-B9D25049B8C2" vnum="2">
<hideElementsInCurrentOnly>false</hideElementsInCurrentOnly>
<bounds x="352" y="20" width="326" height="114"/>
<generatorID>0B1D5703-259A-FE9E-9779-3F77A98AFD49</generatorID>
</OView>
<OView class="oracle.dbtools.crest.swingui.relational.TVTable" oid="A98EFD74-88DE-12CA-8E50-3AB92A1BB45A" otype="Table" vid="6975C3BB-8588-0E10-6BAB-868E81C83CE2" vnum="3">
<hideElementsInCurrentOnly>false</hideElementsInCurrentOnly>
<bounds x="167" y="190" width="332" height="96"/>
<generatorID>D9AF0D8B-76DD-9D6C-AFC6-EE7F6AA1657A</generatorID>
</OView>
<OView class="oracle.dbtools.crest.swingui.relational.TVTable" oid="A98EFD74-88DE-12CA-8E50-3AB92A1BB45A" otype="Table" vid="EB89B26A-395A-00E0-1E6F-C378C29B4336" vnum="4">
<hideElementsInCurrentOnly>false</hideElementsInCurrentOnly>
<bounds x="87" y="453" width="288" height="72"/>
<generatorID>98768C26-468B-BA2B-1DBE-9E6E8618A4A1</generatorID>
</OView>
<OView class="oracle.dbtools.crest.swingui.relational.TVTable" oid="A98EFD74-88DE-12CA-8E50-3AB92A1BB45A" otype="Table" vid="966289ED-8F43-C161-A423-7DAE6C7A307A" vnum="5">
<hideElementsInCurrentOnly>false</hideElementsInCurrentOnly>
<bounds x="387" y="453" width="355" height="72"/>
<generatorID>4522B43E-AA7F-8F50-5761-9AE6F86554C6</generatorID>
</OView>
<OView class="oracle.dbtools.crest.swingui.relational.TVTable" oid="E58C3E1B-6B44-4262-A3E9-05400ABE9087" otype="Table" vid="33F8F093-82E3-7242-5889-E3999A1371CB">
<hideElementsInCurrentOnly>false</hideElementsInCurrentOnly>
<bounds x="962" y="20" width="213" height="100"/>
<generatorID>E61F98D8-B842-DE20-CF4F-3F92D37209CF</generatorID>
</OView>
<OView class="oracle.dbtools.crest.swingui.relational.TVTable" oid="F6CAC769-0AD6-BEAE-BA3C-5FC66A53A6E4" otype="Table" vid="FE5FEFFB-AB32-3DE4-A4E1-0B06C0EDC55B">
<hideElementsInCurrentOnly>false</hideElementsInCurrentOnly>
<bounds x="3" y="571" width="458" height="82"/>
<generatorID>634C41BF-697C-E68A-03C5-95A002AFB452</generatorID>
</OView>
</objectViews>
<connectors>
<Connector class="oracle.dbtools.crest.swingui.relational.TVFKRelation" oid="02D88455-120D-BA4E-9861-93990A236454" otype="FKIndexAssociation" vid_source="F3EBC20E-1F04-413B-D858-A5EE13626F3C" vid_target="FE5FEFFB-AB32-3DE4-A4E1-0B06C0EDC55B">
<hideElementsInCurrentOnly>false</hideElementsInCurrentOnly>
<backgroundColor>-16777216</backgroundColor>
<lineWidth>1</lineWidth>
<points>
<point x="149" y="186"/>
<point x="431" y="653"/>
</points>
</Connector>
<Connector class="oracle.dbtools.crest.swingui.relational.TVFKRelation" oid="0ABCC328-DBEF-B563-CE74-D199F67BC285" otype="FKIndexAssociation" vid_source="F3EBC20E-1F04-413B-D858-A5EE13626F3C" vid_target="FE5FEFFB-AB32-3DE4-A4E1-0B06C0EDC55B">
<hideElementsInCurrentOnly>false</hideElementsInCurrentOnly>
<backgroundColor>-16777216</backgroundColor>
<lineWidth>1</lineWidth>
<points>
<point x="149" y="186"/>
<point x="161" y="653"/>
</points>
</Connector>
<Connector class="oracle.dbtools.crest.swingui.relational.TVFKRelation" oid="0CA38F66-6711-FF51-1279-E65316956B82" otype="FKIndexAssociation" vid_source="1428A2AD-0015-9D25-E352-292308B64C3B" vid_target="FE5FEFFB-AB32-3DE4-A4E1-0B06C0EDC55B">
<hideElementsInCurrentOnly>false</hideElementsInCurrentOnly>
<backgroundColor>-16777216</backgroundColor>
<lineWidth>1</lineWidth>
<points>
<point x="503" y="385"/>
<point x="461" y="653"/>
</points>
</Connector>
<Connector class="oracle.dbtools.crest.swingui.relational.TVFKRelation" oid="0E476D45-18F4-8530-2BD3-E6BADFC0DF72" otype="FKIndexAssociation" vid_source="F3EBC20E-1F04-413B-D858-A5EE13626F3C" vid_target="FE5FEFFB-AB32-3DE4-A4E1-0B06C0EDC55B">
<hideElementsInCurrentOnly>false</hideElementsInCurrentOnly>
<backgroundColor>-16777216</backgroundColor>
<lineWidth>1</lineWidth>
<points>
<point x="149" y="186"/>
<point x="56" y="653"/>
</points>
</Connector>
<Connector class="oracle.dbtools.crest.swingui.relational.TVFKRelation" oid="0ECC508B-5938-64CB-4F08-5E1D1AB66A5F" otype="FKIndexAssociation" vid_source="F3EBC20E-1F04-413B-D858-A5EE13626F3C" vid_target="FE5FEFFB-AB32-3DE4-A4E1-0B06C0EDC55B">
<hideElementsInCurrentOnly>false</hideElementsInCurrentOnly>
<backgroundColor>-16777216</backgroundColor>
<lineWidth>1</lineWidth>
<points>
<point x="149" y="186"/>
<point x="356" y="653"/>
</points>
</Connector>
<Connector class="oracle.dbtools.crest.swingui.relational.TVFKRelation" oid="10E4288D-02AD-68A6-E9EE-C66EC900B1A9" otype="FKIndexAssociation" vid_source="1428A2AD-0015-9D25-E352-292308B64C3B" vid_target="FE5FEFFB-AB32-3DE4-A4E1-0B06C0EDC55B">
<hideElementsInCurrentOnly>false</hideElementsInCurrentOnly>
<backgroundColor>-16777216</backgroundColor>
<lineWidth>1</lineWidth>
<points>
<point x="503" y="385"/>
<point x="461" y="653"/>
</points>
</Connector>
<Connector class="oracle.dbtools.crest.swingui.relational.TVFKRelation" oid="176AF8CC-A4B3-0447-43EF-3C27F946527D" otype="FKIndexAssociation" vid_source="F3EBC20E-1F04-413B-D858-A5EE13626F3C" vid_target="FE5FEFFB-AB32-3DE4-A4E1-0B06C0EDC55B">
<hideElementsInCurrentOnly>false</hideElementsInCurrentOnly>
<backgroundColor>-16777216</backgroundColor>
<lineWidth>1</lineWidth>
<points>
<point x="149" y="186"/>
<point x="251" y="653"/>
</points>
</Connector>
<Connector class="oracle.dbtools.crest.swingui.relational.TVFKRelation" oid="17E39F25-5A46-7090-3A1E-6E5C47E64344" otype="FKIndexAssociation" vid_source="D404A8A7-4CFC-CE33-8043-6CF58B8D2807" vid_target="1428A2AD-0015-9D25-E352-292308B64C3B">
<hideElementsInCurrentOnly>false</hideElementsInCurrentOnly>
<backgroundColor>-16777216</backgroundColor>
<lineWidth>1</lineWidth>
<points>
<point x="924" y="70"/>
<point x="503" y="402"/>
</points>
</Connector>
<Connector class="oracle.dbtools.crest.swingui.relational.TVFKRelation" oid="1CBEBDD1-45E9-F602-9720-B4B765C7262D" otype="FKIndexAssociation" vid_source="F3EBC20E-1F04-413B-D858-A5EE13626F3C" vid_target="FE5FEFFB-AB32-3DE4-A4E1-0B06C0EDC55B">
<hideElementsInCurrentOnly>false</hideElementsInCurrentOnly>
<backgroundColor>-16777216</backgroundColor>
<lineWidth>1</lineWidth>
<points>
<point x="149" y="186"/>
<point x="101" y="653"/>
</points>
</Connector>
<Connector class="oracle.dbtools.crest.swingui.relational.TVFKRelation" oid="27A27281-5463-92BF-230A-C369B295527C" otype="FKIndexAssociation" vid_source="33F8F093-82E3-7242-5889-E3999A1371CB" vid_target="D404A8A7-4CFC-CE33-8043-6CF58B8D2807">
<hideElementsInCurrentOnly>false</hideElementsInCurrentOnly>
<backgroundColor>-16777216</backgroundColor>
<lineWidth>1</lineWidth>
<points>
<point x="1175" y="120"/>
<point x="924" y="54"/>
</points>
</Connector>
<Connector class="oracle.dbtools.crest.swingui.relational.TVFKRelation" oid="29CE4355-21C7-449F-167F-72F2EDF4B36D" otype="FKIndexAssociation" vid_source="1428A2AD-0015-9D25-E352-292308B64C3B" vid_target="FE5FEFFB-AB32-3DE4-A4E1-0B06C0EDC55B">
<hideElementsInCurrentOnly>false</hideElementsInCurrentOnly>
<backgroundColor>-16777216</backgroundColor>
<lineWidth>1</lineWidth>
<points>
<point x="503" y="385"/>
<point x="461" y="653"/>
</points>
</Connector>
<Connector class="oracle.dbtools.crest.swingui.relational.TVFKRelation" oid="2D27001B-2A83-B434-3414-F121CFC6A33B" otype="FKIndexAssociation" vid_source="1428A2AD-0015-9D25-E352-292308B64C3B" vid_target="FE5FEFFB-AB32-3DE4-A4E1-0B06C0EDC55B">
<hideElementsInCurrentOnly>false</hideElementsInCurrentOnly>
<backgroundColor>-16777216</backgroundColor>
<lineWidth>1</lineWidth>
<points>
<point x="503" y="385"/>
<point x="461" y="653"/>
</points>
</Connector>
<Connector class="oracle.dbtools.crest.swingui.relational.TVFKRelation" oid="2FFCBBFA-51CE-B93B-4597-F2E32C471CD2" otype="FKIndexAssociation" vid_source="F3EBC20E-1F04-413B-D858-A5EE13626F3C" vid_target="FE5FEFFB-AB32-3DE4-A4E1-0B06C0EDC55B">
<hideElementsInCurrentOnly>false</hideElementsInCurrentOnly>
<backgroundColor>-16777216</backgroundColor>
<lineWidth>1</lineWidth>
<points>
<point x="149" y="186"/>
<point x="461" y="635"/>
</points>
</Connector>
<Connector class="oracle.dbtools.crest.swingui.relational.TVFKRelation" oid="40559C18-4292-2A66-A90F-37BC535CD824" otype="FKIndexAssociation" vid_source="1428A2AD-0015-9D25-E352-292308B64C3B" vid_target="FE5FEFFB-AB32-3DE4-A4E1-0B06C0EDC55B">
<hideElementsInCurrentOnly>false</hideElementsInCurrentOnly>
<backgroundColor>-16777216</backgroundColor>
<lineWidth>1</lineWidth>
<points>
<point x="503" y="385"/>
<point x="461" y="653"/>
</points>
</Connector>
<Connector class="oracle.dbtools.crest.swingui.relational.TVFKRelation" oid="43C4ABE9-6F30-330D-1626-E17BE2DFA0BB" otype="FKIndexAssociation" vid_source="1428A2AD-0015-9D25-E352-292308B64C3B" vid_target="FE5FEFFB-AB32-3DE4-A4E1-0B06C0EDC55B">
<hideElementsInCurrentOnly>false</hideElementsInCurrentOnly>
<backgroundColor>-16777216</backgroundColor>
<lineWidth>1</lineWidth>
<points>
<point x="503" y="385"/>
<point x="461" y="653"/>
</points>
</Connector>
<Connector class="oracle.dbtools.crest.swingui.relational.TVFKRelation" oid="482CEE00-922D-AEA9-5D9B-0FE9CA1C00E2" otype="FKIndexAssociation" vid_source="1428A2AD-0015-9D25-E352-292308B64C3B" vid_target="FE5FEFFB-AB32-3DE4-A4E1-0B06C0EDC55B">
<hideElementsInCurrentOnly>false</hideElementsInCurrentOnly>
<backgroundColor>-16777216</backgroundColor>
<lineWidth>1</lineWidth>
<points>
<point x="503" y="385"/>
<point x="461" y="653"/>
</points>
</Connector>
<Connector class="oracle.dbtools.crest.swingui.relational.TVFKRelation" oid="486143CC-76F0-B9A9-2C0A-2254B05AC419" otype="FKIndexAssociation" vid_source="F3EBC20E-1F04-413B-D858-A5EE13626F3C" vid_target="FE5FEFFB-AB32-3DE4-A4E1-0B06C0EDC55B">
<hideElementsInCurrentOnly>false</hideElementsInCurrentOnly>
<backgroundColor>-16777216</backgroundColor>
<lineWidth>1</lineWidth>
<points>
<point x="149" y="186"/>
<point x="341" y="653"/>
</points>
</Connector>
<Connector class="oracle.dbtools.crest.swingui.relational.TVFKRelation" oid="51E3DD43-920E-E796-6727-7C0E66D6E8F5" otype="FKIndexAssociation" vid_source="1428A2AD-0015-9D25-E352-292308B64C3B" vid_target="FE5FEFFB-AB32-3DE4-A4E1-0B06C0EDC55B">
<hideElementsInCurrentOnly>false</hideElementsInCurrentOnly>
<backgroundColor>-16777216</backgroundColor>
<lineWidth>1</lineWidth>
<points>
<point x="503" y="385"/>
<point x="461" y="653"/>
</points>
</Connector>
<Connector class="oracle.dbtools.crest.swingui.relational.TVFKRelation" oid="56C7580C-938A-8574-275C-66E781A6F302" otype="FKIndexAssociation" vid_source="F3EBC20E-1F04-413B-D858-A5EE13626F3C" vid_target="FE5FEFFB-AB32-3DE4-A4E1-0B06C0EDC55B">
<hideElementsInCurrentOnly>false</hideElementsInCurrentOnly>
<backgroundColor>-16777216</backgroundColor>
<lineWidth>1</lineWidth>
<points>
<point x="149" y="186"/>
<point x="461" y="635"/>
</points>
</Connector>
<Connector class="oracle.dbtools.crest.swingui.relational.TVFKRelation" oid="56DEC1DC-97E0-F3CF-EABA-799C57DB5DE6" otype="FKIndexAssociation" vid_source="F3EBC20E-1F04-413B-D858-A5EE13626F3C" vid_target="FE5FEFFB-AB32-3DE4-A4E1-0B06C0EDC55B">
<hideElementsInCurrentOnly>false</hideElementsInCurrentOnly>
<backgroundColor>-16777216</backgroundColor>
<lineWidth>1</lineWidth>
<points>
<point x="149" y="186"/>
<point x="191" y="653"/>
</points>
</Connector>
<Connector class="oracle.dbtools.crest.swingui.relational.TVFKRelation" oid="5C67D647-9FB0-38B0-A0F9-A9B24ACB6BEC" otype="FKIndexAssociation" vid_source="F3EBC20E-1F04-413B-D858-A5EE13626F3C" vid_target="FE5FEFFB-AB32-3DE4-A4E1-0B06C0EDC55B">
<hideElementsInCurrentOnly>false</hideElementsInCurrentOnly>
<backgroundColor>-16777216</backgroundColor>
<lineWidth>1</lineWidth>
<points>
<point x="149" y="186"/>
<point x="281" y="653"/>
</points>
</Connector>
<Connector class="oracle.dbtools.crest.swingui.relational.TVFKRelation" oid="5E6841E1-80D0-33BA-E8D6-BE0BF80D1FF8" otype="FKIndexAssociation" vid_source="1428A2AD-0015-9D25-E352-292308B64C3B" vid_target="FE5FEFFB-AB32-3DE4-A4E1-0B06C0EDC55B">
<hideElementsInCurrentOnly>false</hideElementsInCurrentOnly>
<backgroundColor>-16777216</backgroundColor>
<lineWidth>1</lineWidth>
<points>
<point x="503" y="385"/>
<point x="461" y="653"/>
</points>
</Connector>
<Connector class="oracle.dbtools.crest.swingui.relational.TVFKRelation" oid="5E84270C-4399-139E-4A4B-ABD7FC3B3829" otype="FKIndexAssociation" vid_source="1428A2AD-0015-9D25-E352-292308B64C3B" vid_target="FE5FEFFB-AB32-3DE4-A4E1-0B06C0EDC55B">
<hideElementsInCurrentOnly>false</hideElementsInCurrentOnly>
<backgroundColor>-16777216</backgroundColor>
<lineWidth>1</lineWidth>
<points>
<point x="503" y="385"/>
<point x="461" y="653"/>
</points>
</Connector>
<Connector class="oracle.dbtools.crest.swingui.relational.TVFKRelation" oid="6491789E-C332-4586-54A7-30DA0498E2A2" otype="FKIndexAssociation" vid_source="F3EBC20E-1F04-413B-D858-A5EE13626F3C" vid_target="FE5FEFFB-AB32-3DE4-A4E1-0B06C0EDC55B">
<hideElementsInCurrentOnly>false</hideElementsInCurrentOnly>
<backgroundColor>-16777216</backgroundColor>
<lineWidth>1</lineWidth>
<points>
<point x="149" y="186"/>
<point x="371" y="653"/>
</points>
</Connector>
<Connector class="oracle.dbtools.crest.swingui.relational.TVFKRelation" oid="66A0A053-973D-2940-2540-91D352E61667" otype="FKIndexAssociation" vid_source="1428A2AD-0015-9D25-E352-292308B64C3B" vid_target="FE5FEFFB-AB32-3DE4-A4E1-0B06C0EDC55B">
<hideElementsInCurrentOnly>false</hideElementsInCurrentOnly>
<backgroundColor>-16777216</backgroundColor>
<lineWidth>1</lineWidth>
<points>
<point x="503" y="385"/>
<point x="461" y="653"/>
</points>
</Connector>
<Connector class="oracle.dbtools.crest.swingui.relational.TVFKRelation" oid="69567D22-6E63-E2F4-C701-019A70BCB41F" otype="FKIndexAssociation" vid_source="1428A2AD-0015-9D25-E352-292308B64C3B" vid_target="FE5FEFFB-AB32-3DE4-A4E1-0B06C0EDC55B">
<hideElementsInCurrentOnly>false</hideElementsInCurrentOnly>
<backgroundColor>-16777216</backgroundColor>
<lineWidth>1</lineWidth>
<points>
<point x="503" y="385"/>
<point x="461" y="653"/>
</points>
</Connector>
<Connector class="oracle.dbtools.crest.swingui.relational.TVFKRelation" oid="6EC7E072-19D0-5FBF-5619-230B464E181F" otype="FKIndexAssociation" vid_source="1428A2AD-0015-9D25-E352-292308B64C3B" vid_target="FE5FEFFB-AB32-3DE4-A4E1-0B06C0EDC55B">
<hideElementsInCurrentOnly>false</hideElementsInCurrentOnly>
<backgroundColor>-16777216</backgroundColor>
<lineWidth>1</lineWidth>
<points>
<point x="503" y="385"/>
<point x="461" y="653"/>
</points>
</Connector>
<Connector class="oracle.dbtools.crest.swingui.relational.TVFKRelation" oid="730AAADD-240B-9F86-9F37-2384B6B9DC99" otype="FKIndexAssociation" vid_source="1428A2AD-0015-9D25-E352-292308B64C3B" vid_target="FE5FEFFB-AB32-3DE4-A4E1-0B06C0EDC55B">
<hideElementsInCurrentOnly>false</hideElementsInCurrentOnly>
<backgroundColor>-16777216</backgroundColor>
<lineWidth>1</lineWidth>
<points>
<point x="503" y="385"/>
<point x="461" y="653"/>
</points>
</Connector>
<Connector class="oracle.dbtools.crest.swingui.relational.TVFKRelation" oid="759AEE4E-32D6-3CC2-1CB7-FEDEA54E4F1E" otype="FKIndexAssociation" vid_source="F3EBC20E-1F04-413B-D858-A5EE13626F3C" vid_target="FE5FEFFB-AB32-3DE4-A4E1-0B06C0EDC55B">
<hideElementsInCurrentOnly>false</hideElementsInCurrentOnly>
<backgroundColor>-16777216</backgroundColor>
<lineWidth>1</lineWidth>
<points>
<point x="149" y="186"/>
<point x="311" y="653"/>
</points>
</Connector>
<Connector class="oracle.dbtools.crest.swingui.relational.TVFKRelation" oid="765F9B2D-B71A-D7A9-5876-85F53BC1C24F" otype="FKIndexAssociation" vid_source="F3EBC20E-1F04-413B-D858-A5EE13626F3C" vid_target="FE5FEFFB-AB32-3DE4-A4E1-0B06C0EDC55B">
<hideElementsInCurrentOnly>false</hideElementsInCurrentOnly>
<backgroundColor>-16777216</backgroundColor>
<lineWidth>1</lineWidth>
<points>
<point x="149" y="186"/>
<point x="206" y="653"/>
</points>
</Connector>
<Connector class="oracle.dbtools.crest.swingui.relational.TVFKRelation" oid="79239563-0CCB-8315-9B1A-25F38D27039F" otype="FKIndexAssociation" vid_source="F3EBC20E-1F04-413B-D858-A5EE13626F3C" vid_target="FE5FEFFB-AB32-3DE4-A4E1-0B06C0EDC55B">
<hideElementsInCurrentOnly>false</hideElementsInCurrentOnly>
<backgroundColor>-16777216</backgroundColor>
<lineWidth>1</lineWidth>
<points>
<point x="149" y="186"/>
<point x="326" y="653"/>
</points>
</Connector>
<Connector class="oracle.dbtools.crest.swingui.relational.TVFKRelation" oid="7DBBA956-0BC0-BAB7-042C-2FF77A86748D" otype="FKIndexAssociation" vid_source="F3EBC20E-1F04-413B-D858-A5EE13626F3C" vid_target="FE5FEFFB-AB32-3DE4-A4E1-0B06C0EDC55B">
<hideElementsInCurrentOnly>false</hideElementsInCurrentOnly>
<backgroundColor>-16777216</backgroundColor>
<lineWidth>1</lineWidth>
<points>
<point x="149" y="186"/>
<point x="296" y="653"/>
</points>
</Connector>
<Connector class="oracle.dbtools.crest.swingui.relational.TVFKRelation" oid="931EFD57-15AC-5F93-7ED6-CFF384BA065A" otype="FKIndexAssociation" vid_source="1428A2AD-0015-9D25-E352-292308B64C3B" vid_target="FE5FEFFB-AB32-3DE4-A4E1-0B06C0EDC55B">
<hideElementsInCurrentOnly>false</hideElementsInCurrentOnly>
<backgroundColor>-16777216</backgroundColor>
<lineWidth>1</lineWidth>
<points>
<point x="503" y="385"/>
<point x="461" y="653"/>
</points>
</Connector>
<Connector class="oracle.dbtools.crest.swingui.relational.TVFKRelation" oid="99F2CCB3-372B-233A-9F67-8696163B6E8B" otype="FKIndexAssociation" vid_source="1428A2AD-0015-9D25-E352-292308B64C3B" vid_target="FE5FEFFB-AB32-3DE4-A4E1-0B06C0EDC55B">
<hideElementsInCurrentOnly>false</hideElementsInCurrentOnly>
<backgroundColor>-16777216</backgroundColor>
<lineWidth>1</lineWidth>
<points>
<point x="503" y="385"/>
<point x="461" y="653"/>
</points>
</Connector>
<Connector class="oracle.dbtools.crest.swingui.relational.TVFKRelation" oid="9B852157-185A-F59A-EBBC-3D143D1F422E" otype="FKIndexAssociation" vid_source="F3EBC20E-1F04-413B-D858-A5EE13626F3C" vid_target="FE5FEFFB-AB32-3DE4-A4E1-0B06C0EDC55B">
<hideElementsInCurrentOnly>false</hideElementsInCurrentOnly>
<backgroundColor>-16777216</backgroundColor>
<lineWidth>1</lineWidth>
<points>
<point x="149" y="186"/>
<point x="416" y="653"/>
</points>
</Connector>
<Connector class="oracle.dbtools.crest.swingui.relational.TVFKRelation" oid="9DFD6B89-0BA3-F31E-A2ED-B5137225C92B" otype="FKIndexAssociation" vid_source="F3EBC20E-1F04-413B-D858-A5EE13626F3C" vid_target="FE5FEFFB-AB32-3DE4-A4E1-0B06C0EDC55B">
<hideElementsInCurrentOnly>false</hideElementsInCurrentOnly>
<backgroundColor>-16777216</backgroundColor>
<lineWidth>1</lineWidth>
<points>
<point x="149" y="186"/>
<point x="236" y="653"/>
</points>
</Connector>
<Connector class="oracle.dbtools.crest.swingui.relational.TVFKRelation" oid="A46D42B6-F1D5-F1A5-33E4-5237CA516C6A" otype="FKIndexAssociation" vid_source="1428A2AD-0015-9D25-E352-292308B64C3B" vid_target="FE5FEFFB-AB32-3DE4-A4E1-0B06C0EDC55B">
<hideElementsInCurrentOnly>false</hideElementsInCurrentOnly>
<backgroundColor>-16777216</backgroundColor>
<lineWidth>1</lineWidth>
<points>
<point x="503" y="385"/>
<point x="461" y="653"/>
</points>
</Connector>
<Connector class="oracle.dbtools.crest.swingui.relational.TVFKRelation" oid="A6C7F6BA-F74B-4971-CC24-979E0CBA99EA" otype="FKIndexAssociation" vid_source="1428A2AD-0015-9D25-E352-292308B64C3B" vid_target="FE5FEFFB-AB32-3DE4-A4E1-0B06C0EDC55B">
<hideElementsInCurrentOnly>false</hideElementsInCurrentOnly>
<backgroundColor>-16777216</backgroundColor>
<lineWidth>1</lineWidth>
<points>
<point x="503" y="385"/>
<point x="461" y="653"/>
</points>
</Connector>
<Connector class="oracle.dbtools.crest.swingui.relational.TVFKRelation" oid="A9FB76F7-DC23-3111-1DC3-46C26A33BC81" otype="FKIndexAssociation" vid_source="1428A2AD-0015-9D25-E352-292308B64C3B" vid_target="FE5FEFFB-AB32-3DE4-A4E1-0B06C0EDC55B">
<hideElementsInCurrentOnly>false</hideElementsInCurrentOnly>
<backgroundColor>-16777216</backgroundColor>
<lineWidth>1</lineWidth>
<points>
<point x="503" y="385"/>
<point x="461" y="653"/>
</points>
</Connector>
<Connector class="oracle.dbtools.crest.swingui.relational.TVFKRelation" oid="AA9DFA01-7FB3-31DD-7AF2-B69273D850BC" otype="FKIndexAssociation" vid_source="F3EBC20E-1F04-413B-D858-A5EE13626F3C" vid_target="FE5FEFFB-AB32-3DE4-A4E1-0B06C0EDC55B">
<hideElementsInCurrentOnly>false</hideElementsInCurrentOnly>
<backgroundColor>-16777216</backgroundColor>
<lineWidth>1</lineWidth>
<points>
<point x="149" y="186"/>
<point x="266" y="653"/>
</points>
</Connector>
<Connector class="oracle.dbtools.crest.swingui.relational.TVFKRelation" oid="AC142A06-4B5D-6D68-91C8-07755154E393" otype="FKIndexAssociation" vid_source="1428A2AD-0015-9D25-E352-292308B64C3B" vid_target="FE5FEFFB-AB32-3DE4-A4E1-0B06C0EDC55B">
<hideElementsInCurrentOnly>false</hideElementsInCurrentOnly>
<backgroundColor>-16777216</backgroundColor>
<lineWidth>1</lineWidth>
<points>
<point x="503" y="385"/>
<point x="461" y="653"/>
</points>
</Connector>
<Connector class="oracle.dbtools.crest.swingui.relational.TVFKRelation" oid="AD68821F-87A6-2B8D-E6EE-D4582909D34D" otype="FKIndexAssociation" vid_source="F3EBC20E-1F04-413B-D858-A5EE13626F3C" vid_target="FE5FEFFB-AB32-3DE4-A4E1-0B06C0EDC55B">
<hideElementsInCurrentOnly>false</hideElementsInCurrentOnly>
<backgroundColor>-16777216</backgroundColor>
<lineWidth>1</lineWidth>
<points>
<point x="149" y="186"/>
<point x="71" y="653"/>
</points>
</Connector>
<Connector class="oracle.dbtools.crest.swingui.relational.TVFKRelation" oid="B1CE1EC8-FA39-068B-67C7-A298A2BBFBEA" otype="FKIndexAssociation" vid_source="1428A2AD-0015-9D25-E352-292308B64C3B" vid_target="FE5FEFFB-AB32-3DE4-A4E1-0B06C0EDC55B">
<hideElementsInCurrentOnly>false</hideElementsInCurrentOnly>
<backgroundColor>-16777216</backgroundColor>
<lineWidth>1</lineWidth>
<points>
<point x="503" y="385"/>
<point x="461" y="653"/>
</points>
</Connector>
<Connector class="oracle.dbtools.crest.swingui.relational.TVFKRelation" oid="B70F4258-14A6-3DD5-3104-2CEE93ECA86C" otype="FKIndexAssociation" vid_source="F3EBC20E-1F04-413B-D858-A5EE13626F3C" vid_target="FE5FEFFB-AB32-3DE4-A4E1-0B06C0EDC55B">
<hideElementsInCurrentOnly>false</hideElementsInCurrentOnly>
<backgroundColor>-16777216</backgroundColor>
<lineWidth>1</lineWidth>
<points>
<point x="149" y="186"/>
<point x="176" y="653"/>
</points>
</Connector>
<Connector class="oracle.dbtools.crest.swingui.relational.TVFKRelation" oid="BF1775F1-ED3D-DA2B-BBF2-032E68AEC4F3" otype="FKIndexAssociation" vid_source="F3EBC20E-1F04-413B-D858-A5EE13626F3C" vid_target="FE5FEFFB-AB32-3DE4-A4E1-0B06C0EDC55B">
<hideElementsInCurrentOnly>false</hideElementsInCurrentOnly>
<backgroundColor>-16777216</backgroundColor>
<lineWidth>1</lineWidth>
<points>
<point x="149" y="186"/>
<point x="131" y="653"/>
</points>
</Connector>
<Connector class="oracle.dbtools.crest.swingui.relational.TVFKRelation" oid="C1C24D8A-7AC3-761D-F994-C482E2D4C9FA" otype="FKIndexAssociation" vid_source="F3EBC20E-1F04-413B-D858-A5EE13626F3C" vid_target="FE5FEFFB-AB32-3DE4-A4E1-0B06C0EDC55B">
<hideElementsInCurrentOnly>false</hideElementsInCurrentOnly>
<backgroundColor>-16777216</backgroundColor>
<lineWidth>1</lineWidth>
<points>
<point x="149" y="186"/>
<point x="401" y="653"/>
</points>
</Connector>
<Connector class="oracle.dbtools.crest.swingui.relational.TVFKRelation" oid="CF5E4D9B-6187-0287-5E49-45DBE49AC679" otype="FKIndexAssociation" vid_source="1428A2AD-0015-9D25-E352-292308B64C3B" vid_target="FE5FEFFB-AB32-3DE4-A4E1-0B06C0EDC55B">
<hideElementsInCurrentOnly>false</hideElementsInCurrentOnly>
<backgroundColor>-16777216</backgroundColor>
<lineWidth>1</lineWidth>
<points>
<point x="503" y="385"/>
<point x="461" y="653"/>
</points>
</Connector>
<Connector class="oracle.dbtools.crest.swingui.relational.TVFKRelation" oid="CFFCE10B-2D88-580F-53CE-73AE9E73D49D" otype="FKIndexAssociation" vid_source="1428A2AD-0015-9D25-E352-292308B64C3B" vid_target="FE5FEFFB-AB32-3DE4-A4E1-0B06C0EDC55B">
<hideElementsInCurrentOnly>false</hideElementsInCurrentOnly>
<backgroundColor>-16777216</backgroundColor>
<lineWidth>1</lineWidth>
<points>
<point x="503" y="385"/>
<point x="461" y="653"/>
</points>
</Connector>
<Connector class="oracle.dbtools.crest.swingui.relational.TVFKRelation" oid="D23CD537-C993-1493-D143-594DAA43C3FC" otype="FKIndexAssociation" vid_source="1428A2AD-0015-9D25-E352-292308B64C3B" vid_target="FE5FEFFB-AB32-3DE4-A4E1-0B06C0EDC55B">
<hideElementsInCurrentOnly>false</hideElementsInCurrentOnly>
<backgroundColor>-16777216</backgroundColor>
<lineWidth>1</lineWidth>
<points>
<point x="503" y="385"/>
<point x="461" y="653"/>
</points>
</Connector>
<Connector class="oracle.dbtools.crest.swingui.relational.TVFKRelation" oid="D536647B-B2F2-2B48-F9EF-FBCD2C878F26" otype="FKIndexAssociation" vid_source="1428A2AD-0015-9D25-E352-292308B64C3B" vid_target="FE5FEFFB-AB32-3DE4-A4E1-0B06C0EDC55B">
<hideElementsInCurrentOnly>false</hideElementsInCurrentOnly>
<backgroundColor>-16777216</backgroundColor>
<lineWidth>1</lineWidth>
<points>
<point x="503" y="385"/>
<point x="461" y="653"/>
</points>
</Connector>
<Connector class="oracle.dbtools.crest.swingui.relational.TVFKRelation" oid="D62A7261-082B-C6EA-0247-BD9DAD7F4FAF" otype="FKIndexAssociation" vid_source="F3EBC20E-1F04-413B-D858-A5EE13626F3C" vid_target="FE5FEFFB-AB32-3DE4-A4E1-0B06C0EDC55B">
<hideElementsInCurrentOnly>false</hideElementsInCurrentOnly>
<backgroundColor>-16777216</backgroundColor>
<lineWidth>1</lineWidth>
<points>
<point x="149" y="186"/>
<point x="386" y="653"/>
</points>
</Connector>
<Connector class="oracle.dbtools.crest.swingui.relational.TVFKRelation" oid="D63DA31F-7A4D-96CC-D8F0-5BC1EFDD18D1" otype="FKIndexAssociation" vid_source="1428A2AD-0015-9D25-E352-292308B64C3B" vid_target="FE5FEFFB-AB32-3DE4-A4E1-0B06C0EDC55B">
<hideElementsInCurrentOnly>false</hideElementsInCurrentOnly>
<backgroundColor>-16777216</backgroundColor>
<lineWidth>1</lineWidth>
<points>
<point x="503" y="385"/>
<point x="461" y="653"/>
</points>
</Connector>
<Connector class="oracle.dbtools.crest.swingui.relational.TVFKRelation" oid="DD9895A2-0FE2-F4FF-6402-4BE98F1B580D" otype="FKIndexAssociation" vid_source="1428A2AD-0015-9D25-E352-292308B64C3B" vid_target="FE5FEFFB-AB32-3DE4-A4E1-0B06C0EDC55B">
<hideElementsInCurrentOnly>false</hideElementsInCurrentOnly>
<backgroundColor>-16777216</backgroundColor>
<lineWidth>1</lineWidth>
<points>
<point x="503" y="385"/>
<point x="461" y="653"/>
</points>
</Connector>
<Connector class="oracle.dbtools.crest.swingui.relational.TVFKRelation" oid="E9D5FDD2-7789-605C-BDCC-1050DB719D5D" otype="FKIndexAssociation" vid_source="F3EBC20E-1F04-413B-D858-A5EE13626F3C" vid_target="FE5FEFFB-AB32-3DE4-A4E1-0B06C0EDC55B">
<hideElementsInCurrentOnly>false</hideElementsInCurrentOnly>
<backgroundColor>-16777216</backgroundColor>
<lineWidth>1</lineWidth>
<points>
<point x="149" y="186"/>
<point x="221" y="653"/>
</points>
</Connector>
<Connector class="oracle.dbtools.crest.swingui.relational.TVFKRelation" oid="EF179C54-4C68-CE23-2588-D440FCB7AE08" otype="FKIndexAssociation" vid_source="1428A2AD-0015-9D25-E352-292308B64C3B" vid_target="FE5FEFFB-AB32-3DE4-A4E1-0B06C0EDC55B">
<hideElementsInCurrentOnly>false</hideElementsInCurrentOnly>
<backgroundColor>-16777216</backgroundColor>
<lineWidth>1</lineWidth>
<points>
<point x="503" y="385"/>
<point x="461" y="653"/>
</points>
</Connector>
<Connector class="oracle.dbtools.crest.swingui.relational.TVFKRelation" oid="EF42F387-E746-FEAE-5303-BE97C68F7DF0" otype="FKIndexAssociation" vid_source="F3EBC20E-1F04-413B-D858-A5EE13626F3C" vid_target="FE5FEFFB-AB32-3DE4-A4E1-0B06C0EDC55B">
<hideElementsInCurrentOnly>false</hideElementsInCurrentOnly>
<backgroundColor>-16777216</backgroundColor>
<lineWidth>1</lineWidth>
<points>
<point x="149" y="186"/>
<point x="116" y="653"/>
</points>
</Connector>
<Connector class="oracle.dbtools.crest.swingui.relational.TVFKRelation" oid="F1B873EB-CF8D-505E-0939-CEE5AD7763DB" otype="FKIndexAssociation" vid_source="F3EBC20E-1F04-413B-D858-A5EE13626F3C" vid_target="FE5FEFFB-AB32-3DE4-A4E1-0B06C0EDC55B">
<hideElementsInCurrentOnly>false</hideElementsInCurrentOnly>
<backgroundColor>-16777216</backgroundColor>
<lineWidth>1</lineWidth>
<points>
<point x="149" y="186"/>
<point x="146" y="653"/>
</points>
</Connector>
<Connector class="oracle.dbtools.crest.swingui.relational.TVFKRelation" oid="F22E0BAD-F273-FD65-A08B-798BBE227FF3" otype="FKIndexAssociation" vid_source="F3EBC20E-1F04-413B-D858-A5EE13626F3C" vid_target="FE5FEFFB-AB32-3DE4-A4E1-0B06C0EDC55B">
<hideElementsInCurrentOnly>false</hideElementsInCurrentOnly>
<backgroundColor>-16777216</backgroundColor>
<lineWidth>1</lineWidth>
<points>
<point x="149" y="186"/>
<point x="86" y="653"/>
</points>
</Connector>
</connectors>
</Diagram>
