                <ChangeRequest class="oracle.dbtools.crest.model.ChangeRequest" name="[IReF] Add ISIN to OTC Derivatives" id="29257-496">
                    <createdBy>ostarij</createdBy>
                    <comment>&lt;!--See: documentation on [Issues in GitLab](https://gitlab.sofa.dev/sdd-bird-team/bird-logical-data-model/-/wikis/Issues-in-GitLab)--&gt;

# Overview

IReF is adding the International Securities Identification Number as a requirement for the reporting of Over the Counter (OTC) Derivative instruments. BIRD needs to create a solution for that which is similar in structure to the structure for _Securities_ (see picture)

![image](/uploads/da94ad45559840aa7bc470e7bcdd0d51/image.png){width="707" height="406"}

Current structure for OTC derivatives:

![image.png](/uploads/458e296264e18bf92d503c61852087b7/image.png)

### Contact person

- @Arjan.Bos
- @Olivia.Hauet

### Relevant Framework/Template

- IReF

### Additional documentation/links (optional)

ESMA has a Q&amp;A on this specific topic: https://www.esma.europa.eu/sites/default/files/2024-01/ESMA12-766636679-105_Response_to_EC_consultation_OTC_derivative_identifier.pdf

### Before closing checklist

- [ ] Assignee for review
- [ ] Assignee to close
- [ ] Other actions</comment>
                    <notes>https://gitlab.sofa.dev/sdd-bird-team/bird-logical-data-model/-/issues/496</notes>
                    <ownerDesignName>BIRD data models</ownerDesignName>
                    <engineerTo>
                        <item key="9F71AC75-C64B-3A4F-AE9B-7E0028CEC114" value="true"/>
                        <item key="AEFDAE93-361A-74FC-D9B0-896822C5F2BB" value="true"/>
                        <item key="963C5E00-5517-19DF-A89B-FDB8671036FF" value="true"/>
                        <item key="24FC9E45-18D3-C550-6BAD-4693BE2883E4" value="true"/>
                        <item key="48078BB1-66DB-629F-6B3D-FE6F84461BCA" value="true"/>
                        <item key="6BCEF519-13E1-B08A-2794-C031B6E1ADA6" value="true"/>
                    </engineerTo>
                    <status>proposed</status>
                </ChangeRequest>
