<?xml version = '1.0' encoding = 'UTF-8'?>
<Relation class="oracle.dbtools.crest.model.design.logical.Relation" name="Loan and advance is protected by Protection item via Loan and advance Collateral received assignment" directorySegmentName="seg_0" id="408BE0A4-4DC1-7792-D379-207BF91DFA0F">
<createdBy>Dominik</createdBy>
<createdTime>2021-08-03 15:43:50 UTC</createdTime>
<commentInRDBMS><![CDATA[is protected by]]></commentInRDBMS>
<ownerDesignName>BIRD data models</ownerDesignName>
<engineerTo>
<item key="7AFB6CD5-FA49-A27F-7A6B-F80FB6EE79EC" value="true"/>
<item key="AD51085A-89B5-9B80-E7E5-D958DCB6DFDD" value="true"/>
<item key="EB3349D0-DAC2-8B13-8330-8A909289ACD1" value="true"/>
<item key="8ABAF9E8-1A29-1C57-534B-70C26F5C5191" value="true"/>
</engineerTo>
<sourcePk>5F537373-F972-0198-62B3-B60EA615A290</sourcePk>
<identifying>true</identifying>
<optionalSource>true</optionalSource>
<optionalTarget>false</optionalTarget>
<sourceCardinality>1</sourceCardinality>
<sourceEntity>B6FD5D89-A17A-4780-AA57-0259F91E0630</sourceEntity>
<targetCardinalityString>*</targetCardinalityString>
<targetEntity>ACDEC181-3399-411D-BD18-E28CCC37B7BC</targetEntity>
<transferable>true</transferable>
<deleteRule>NO ACTION</deleteRule>
<changeRequests>
<requestID>34227-511</requestID>
</changeRequests>
</Relation>
